Workbook

Sheet Справка
A1: РАСЧЕТ
A2: стоимости вновь начинаемого объекта дорожных работ (от 10.04.2026)
A4: Государственный заказчик | B4: Краевое государственное казенное учреждение "Управление автомобильных дорог Камчатского края"
A5: Наименование объекта | B5: Строительство причальных сооружений через протоку Озерная в Усть-Камчатском районе Камчатского края
B6: Стоимость работ в ценах на дату утверждения сметной документации 1 квартал 2022 года | C6: Выполнение | D6: Экономия | E6: Стоимость остатка работ в ценах утверждения ПСД, 1 квартал 2022 года | F6: Индекс фактической инфляции | H6: Стоимость работ в ценах на дату формирования начальной (максимальной) цены контракта | K6: Индекс прогнозной инфляции на период выполнения работ Кинф= Д1*К1+Д2*К2+Д3*К3 | M6: Начальная (максимальная) цена контракта с учетом индекса прогнозной инфляции на период выполнения работ | Q6: в том числе по годам | Z6: Стоимость в ценах соответствующих лет | AA6: Подлежит выполнению до конца строительства в ценах соответствующих лет
W7: 2026 (апрель - декабрь) | Y7: 2027 (январь-октябрь) | AB7: 2022 | AC7: 2023 | AD7: 2024
A8: 1 | B8: 2 | C8: 3 | D8: 4 | E8: 5 | F8: 6 | H8: 7 | K8: 8 | M8: 9 | Q8: 10 | W8: 12 | Y8: 13 | Z8: 14 | AA8: 15
A9: Стоимость всего | B9: =B11+B14 -> 271528193 | C9: =C11+C14 -> 12699227 | E9: =E11+E14 -> 258828966 | H9: =H11+H14 -> 3.5476653e+08 | M9: =M11+M14 -> 3.9555597e+08 | W9: =W11+W14 -> 1.1677987e+08 | Y9: =Y11+Y14+0.001 -> 2.787761e+08 | Z9: =Z11+Z14+0.001 -> 4.082552e+08 | AA9: =AA11+AA14+0.001 -> 3.9555597e+08 | AB9: =(U9+C9)/Z9 -> 0.031 | AC9: =(C9+U9+W9)/Z9 -> 0.317 | AD9: =(C9+Y9+U9+W9)/Z9 -> 1
A10: в том числе
A11: Затраты заказчика | B11: =B12+B13 -> 17942395 | C11: =C12+C13 -> 12699227 | E11: =B11-C11 -> 5243168 | F11: =F15 -> 1.399 | M11: =SUM(M12:P13) -> 14050688 | W11: =W12+W13 -> 2328289 | Y11: =Y12 -> 11722399 | Z11: =Z12+Z13 -> 26749915 | AA11: =AA12+AA13 -> 14050688
A12: индексируемые | B12: =Затраты!J11*1000 -> 6243145 | C12: =Затраты!B11*1000 -> 999977 | E12: =B12-C12 -> 5243168 | M12: =U12+W12+Y12 -> 14050688 | W12: =Затраты!E10*Справка!F15*Справка!K15*1000 -> 2328289 | Y12: =Затраты!F10*Справка!F15*Справка!K15*1000 -> 11722399 | Z12: =M12+C12 -> 15050665 | AA12: =M12 -> 14050688
A13: неиндексируемые | B13: =Затраты!I22*1000 -> 11699250 | C13: =Затраты!B22*1000 -> 11699250 | E13: =B13-C13 -> 0 | Z13: =M13+C13 -> 11699250 | AA13: =E13 -> 0 | AB13: =Z9-C9 -> 3.9555597e+08
A14: Затраты подрядчика | B14: =B15+B16 -> 253585798 | E14: =E15+E16 -> 253585798 | H14: =SUM(H15:J16) -> 3.5476653e+08 | M14: =SUM(M15:P16) -> 3.8150528e+08 | W14: =W15+W16 -> 1.1445159e+08 | Y14: =Y15 -> 2.670537e+08 | Z14: =Z15+Z16 -> 3.8150528e+08 | AA14: =AA15+AA16 -> 3.8150528e+08
A15: индексируемые | B15: =Затраты!J26*1000 -> 253585798 | E15: =B15-C15-D15 -> 253585798 | F15: =C41 -> 1.399 | H15: =E15*F15 -> 3.5476653e+08 | K15: =W56 -> 1.07537 | M15: =H15*K15 -> 3.8150528e+08 | W15: =Затраты!E26*1000*Справка!K15*Справка!F15 -> 1.1445159e+08 | Y15: =Затраты!F26*Справка!F15*Справка!K15*1000 -> 2.670537e+08 | Z15: =M15+C15 -> 3.8150528e+08 | AA15: =M15 -> 3.8150528e+08
A16: неиндексируемые | B16: 0
A17: В зависимости от года утверждения ПСД и планируемого выполнения работ по годам исполнения государственного контракта таблица может быть откорректирована.
A19: Дата формирования НМЦК - | B19: апрель 2026 года | X19: из расчета 30% аванса в 2026г. = | AA19: =AA14*0.3 -> 1.1445159e+08
A20: Начало строительства - июнь 2026 года
A21: Окончание строительства - октябрь 2027 года
A23: 1. Расчет индексов фактической инфляции с использованием ИПЦ Росстата (Камчатский край):
A24: март 2023 / март 2022 | B24: 108.6 | C24: =B24/100 -> 1.086
A25: март 2024 / март 2023 | B25: 109.53 | C25: =B25/100 -> 1.0953 | AC25: 2025 = | AD25: 1.082
A26: март 2025 / март 2024 | B26: 106.56 | C26: =B26/100 -> 1.0656
A27: 45748 | B27: 98.08 | C27: =B27/100 -> 0.9808
A28: 45778 | B28: 101.17 | C28: =B28/100 -> 1.0117 | AC28: 2026 = | AD28: 1.078
A29: 45809 | B29: 103.19 | C29: =B29/100 -> 1.0319
A30: 45839 | B30: 100.64 | C30: =B30/100 -> 1.0064
A31: 45870 | B31: 100.15 | C31: =B31/100 -> 1.0015
A32: 45901 | B32: 102.06 | C32: =B32/100 -> 1.0206
A33: 45931 | B33: 100.26 | C33: =B33/100 -> 1.0026
A34: 45962 | B34: 100.86 | C34: =B34/100 -> 1.0086 | E34: 2. Расчет индекса прогнозной инфляции (Уточненный прогноз социально-экономического развития Камчатского края на 2026 год и на плановый период 2027 и 2028 годов от 19 ноября 2025, отрасль "Инвестиции в основной капитал"):
A35: 45992 | B35: 100.46 | C35: =B35/100 -> 1.0046
A36: 46023 | B36: 101.14 | C36: =B36/100 -> 1.0114
A37: 46054 | B37: 100.99 | C37: =B37/100 -> 1.0099
A38: 46082 | B38: 100.99 | C38: =B38/100 -> 1.0099
E40: 2026 = | K40: 12 | L40: √ | M40: =F41 -> 1.078 | N40: = | O40: =M40^(1/K40) -> 1.0063
B41: Индекс фактической инфляции | C41: =C25*C26*C24*C27*C28*C29*C30*C31*C32*C33*C34*C35*C36*C37*C38 -> 1.399 | F41: 1.078
E43: 2027 = | K43: 12 | L43: √ | M43: =F44 -> 1.077 | N43: = | O43: =M43^(1/K43) -> 1.0062
F44: 1.077
A46: Доля сметной стоимости, подлежащая выполнению подрядчиком в 2026 году (Дп2) - | E46: =Затраты!E26/Затраты!J26 -> 0.3 | G46: Доля сметной стоимости, подлежащая выполнению заказчиком в 2026 году (Дз2) - | V46: =Затраты!E10/(Затраты!J10-Затраты!B10) -> 0.29517
A47: Доля сметной стоимости, подлежащая выполнению подрядчиком в 2027 году (Дп3) - | E47: =Затраты!F26/Затраты!J26 -> 0.7 | G47: Доля сметной стоимости, подлежащая выполнению заказчиком в 2027 году (Дз3) - | V47: =Затраты!O11 -> 0.83429
A49: С учетом полученных данных вычисляются прогнозные индексы для каждого периода исполнения контракта:
B52: К на 2026 год = | C52: (1,00639-1) / 2+1 = | L52: = | M52: =(D63-1)/2+1 -> 1.0291
B54: К на 2027 год = | C54: 1,00639*((1,0062+1,006210) / 2) = | L54: = | P54: =D63*(D65+D66)/2 -> 1.0952
A56: Индекс прогнозной инфляции на период выполнения работ (для затрат подрядчик) = | J56: =E46 -> 0.3 | K56: * | L56: =M52 -> 1.0291 | M56: + | N56: =E47 -> 0.7 | P56: * | Q56: * | R56: =X54 -> 0 | T56: = | U56: =P54 -> 1.0952 | V56: = | W56: =F56*H56+J56*L56+N56*U56 -> 1.07537
A58: Индекс прогнозной инфляции на период выполнения работ (для затрат заказчик) = | J58: =V46 -> 0.29517 | K58: * | L58: =M52 -> 1.0291 | M58: + | N58: =V47 -> 0.83429 | P58: * | Q58: * | R58: =#REF! -> #REF! | T58: = | U58: =P54 -> 1.0952 | V58: = | W58: =F58*H58+J58*L58+N58 -> 1.13805
Q59: * | R59: =#REF! -> #REF! | T59: =
A60: Ежемесячный прогнозный индекс | E60: степень | F60: период
B62: 2026 | C62: =O40 -> 1.0063 | D62: =POWER(C62,E62) -> 1.0063 | E62: 1 | F62: январь 2026
C63: =C62 -> 1.0063 | D63: =POWER(C63,E63) -> 1.0582 | E63: 9 | F63: апрель -декабрь 2026
B65: 2027 | C65: =O43 -> 1.0062 | D65: =POWER(C65,E65) -> 1.0062 | E65: 1 | F65: январь 2027
C66: =C65 -> 1.0062 | D66: =POWER(C66,E66) -> 1.0638 | E66: 10 | F66: январь-октябрь 2027

Sheet Затраты
E1: Приложение № 3 к Порядку взаимодействия при рассмотрении стоимостных показателей объектов строительства, реконструкции, капитального ремонта автомобильных дорог и искусственных дорожных сооружений, частично или полностью финансируемых за счет средств федерального бюджета, утвержденному Приказом от 28.07.2021 № 154
A3: Справка о затратах заказчика и затратах подрядчика в составе сводного сметного расчета с расшифровкой по видам затрат
A5: Заказчик: Краевое государственное казенное учреждение "Управление автомобильных дорог Камчатского края"
A6: Наименование объекта: Строитсльство причальных сооружений через протоку Озерная в Усть-Камчатском районе Камчатского края
A8: Наименование работ и затрат | B8: Распределение затрат по годам, тыс. руб. в ценах 1 кв. 2022 г (в уровне цен утвержденной проектной документации) | K8: Обоснование
B9: До 2022 (выполнено) | D9: 2025 | E9: 2026 | F9: 2027 | G9: Экономия | I9: ВСЕГО с НДС 20% | J9: НДС 22% | O9: =F10+E10 -> 9339.464
A10: 1. Затраты заказчика | B10: =B11+B22 -> 12699.227 | D10: =D11+D22 -> 0 | E10: =E11+E22 -> 1547.609 | F10: =F11+F22 -> 7791.855 | G10: =G11+G22 -> 0 | H10: =H11+H22 -> 16486.85 | I10: =I11+I22 -> 17840.047 | J10: =J11+J22 -> 17942.395 | M10: =SUM(B10:G10)-I10 -> 4198.644 | O10: =E10/O9 -> 0.1657064
A11: - индексируемые | B11: =SUM(B12:B18) -> 999.977 | D11: =SUM(D12:D18) -> 0 | E11: =SUM(E12:E18) -> 1547.609 | F11: =SUM(F12:F18) -> 7791.855 | G11: =SUM(G12:G18) -> 0 | H11: =SUM(H12:H18) -> 4787.6 | I11: =SUM(I12:I18) -> 6140.797 | J11: =SUM(J12:J18) -> 6243.145 | M11: =SUM(B11:G11)-I11 -> 4198.644 | O11: =F10/O9 -> 0.8342936
A12: Восстановление оси трассы | E12: =I12-C12-D12 -> 0 | M12: =SUM(B12:G12)-I12 -> 0
A13: Ущерб водным биоресурсам | F13: =J13 -> 632.973 | H13: =173.51+345.32 -> 518.83 | I13: =(173.51+345.32)*1.2 -> 622.596 | J13: =(173.51+345.32)*1.22 -> 632.973 | M13: =SUM(B13:G13)-I13 -> 10.377
E14: =I14-C14-D14 -> 0 | M14: =SUM(B14:G14)-I14 -> 0
A15: Технологическое присоединение к электрическим сетям | F15: =J15 -> 49.203 | H15: =39.86+0.47 -> 40.33 | I15: =(39.86+0.47)*1.2 -> 48.396 | J15: =(39.86+0.47)*1.22 -> 49.203 | M15: =SUM(B15:G15)-I15 -> 0.807
A16: Строительный контроль | E16: =J16/J27*E26 -> 1547.609 | F16: =J16-E16 -> 3611.088 | H16: 4228.44 | I16: =4228.44*1.2 -> 5074.128 | J16: =4228.44*1.22 -> 5158.697 | L16: =I16/(I28+I36+I45) -> 0.021398927 | M16: =SUM(B16:G16)-I16 -> 84.569 | O16: =J13+J15+J16+J30+J31+J32+J36+J43 -> 254454.4 | P16: =O16/1.22 -> 208569.18
A17: Авторский надзор | E17: =J17/2 -> 0 | F17: ='НМЦК АН'!B18/1000 -> 498.591 | L17: =(I28+I36+I45)*0.2% -> 474.24134 | M17: =SUM(B17:G17)-I17 -> 498.591 | O17: =J17+J18+J47 -> 5374.543 | P17: =O17/1.22 -> 4405.3631 | Q17: =P17*1.22 -> 5374.543 | R17: =4405.36*1.22 -> 5374.5392
A18: Непредвиденные затраты: | B18: =SUM(B19:B21) -> 999.977 | D18: =SUM(D19:D21) -> 0 | E18: =SUM(E19:E21) -> 0 | F18: =SUM(F19:F21) -> 3000 | G18: =SUM(G19:G21) -> 0 | I18: =SUM(I19:I21) -> 395.677 | J18: =SUM(J19:J21) -> 402.272 | M18: =SUM(B18:G18)-I18 -> 3604.3 | O18: =J22 -> 11699.25 | R18: =R17/1.22 -> 4405.36
A19: Непредвиденные затраты от прочих затрат заказчика | H19: =(H13+H15+H16+H22)*2% -> 329.737 | I19: =(I13+I15+I16+I22)*2%+I22*0.2*2%-0.007 -> 395.677 | J19: =(J13+J15+J16+J22)*2%+J22*0.22*2%-0.007 -> 402.272 | M19: =SUM(B19:G19)-#REF! -> #REF!
A20: Резерв на непредвиденные работы и затраты от прочих затрат подрядчика (1%) | F20: =J20 -> 0 | L20: =L21+F20+F19+F15+F13 -> #REF! | M20: =SUM(B20:G20)-I19 -> -395.677
A21: Резерв на непредвиденные работы и затраты от СМР (1%) | B21: =O26-B22 -> 999.977 | F21: 3000 | L21: =F21-#REF!/1000 -> #REF! | M21: =SUM(B21:G21)-I21 -> 3999.977
A22: - неиндексируемые | B22: =SUM(B23:B25) -> 11699.25 | D22: =SUM(D23:D25) -> 0 | E22: =SUM(E23:E25) -> 0 | F22: =SUM(F23:F25) -> 0 | G22: =SUM(G23:G25) -> 0 | H22: =SUM(H23:H25) -> 11699.25 | I22: =SUM(I23:I25) -> 11699.25 | J22: =J24+J25 -> 11699.25 | M22: =SUM(B22:G22)-I22 -> 0
A23: Инженерные изыскания | M23: =SUM(B23:G23)-I23 -> 0
A24: Проектные работы | B24: =I24 -> 10000 | H24: 10000 | I24: 10000 | J24: =I24 -> 10000 | M24: =SUM(B24:G24)-I24 -> 0
A25: Экспертиза проекта | B25: =I25 -> 1699.25 | H25: 1699.25 | I25: 1699.25 | J25: =I25 -> 1699.25 | M25: =SUM(B25:G25)-I25 -> 0
A26: 2. Затраты подрядчика, в том числе: | B26: =B27 -> 0 | D26: =D27 -> 0 | E26: =E27 -> 76075.739 | F26: =F27 -> 177510.06 | G26: =G27 -> 0 | H26: =H27 -> 207857.21 | I26: =I27 -> 249428.65 | J26: =J27 -> 253585.8 | M26: =SUM(B26:G26)-I26 -> 4157.146 | O26: =12699.227 -> 12699.227
A27: - индексируемые | B27: =B28+B36+B42+B43+B47 -> 0 | D27: =D28+D36+D42+D43+D47 -> 0 | E27: =E28+E36+E42+E43+E47 -> 76075.739 | F27: =F28+F36+F42+F43+F47 -> 177510.06 | G27: =G28+G36+G42+G43+G47 -> 0 | H27: =H28+H36+H42+H43+H47 -> 207857.21 | I27: =I28+I36+I42+I43+I47 -> 249428.65 | J27: =J28+J36+J42+J43+J47 -> 253585.8 | M27: =SUM(B27:G27)-I27 -> 4157.146
A28: Подготовка территории строительства. Всего | B28: =SUM(B30:B35) -> 0 | D28: =SUM(D30:D35) -> 0 | E28: =SUM(E30:E35) -> 13986.14 | F28: =SUM(F30:F35) -> 0 | H28: =SUM(H30:H35) -> 11464.05 | I28: =SUM(I30:I35) -> 13756.859 | J28: =SUM(J30:J35) -> 13986.14 | L28: =Справка!U9 -> 0 | M28: =SUM(B28:G28)-I28 -> 229.281
A29: в том числе: | M29: =SUM(B29:G29)-I29 -> 0
A30: Демонтаж причальных сооружений | E30: =J30 -> 13949.796 | H30: =7693.11+3741.15 -> 11434.26 | I30: =(7693.11+3741.15)*1.2-0.001 -> 13721.111 | J30: =(7693.11+3741.15)*1.22-0.001 -> 13949.796 | K30: =Справка!AA19 -> 1.1445159e+08 | L30: =Справка!W9 -> 116779874 | M30: =SUM(B30:G30)-I30 -> 228.685
A31: Разборка существующих сооружений | E31: =J31 -> 24.449 | H31: 20.04 | I31: =20.04*1.2 -> 24.048 | J31: =20.04*1.22 -> 24.449 | K31: =Справка!W15 -> 1.1445159e+08 | M31: =SUM(B31:G31)-I31 -> 0.401 | O31: 20649782 | P31: =Справка!W9 -> 1.1677987e+08
A32: Восстановление оси трассы | E32: =J32 -> 11.895 | H32: =7.82+1.93 -> 9.75 | I32: =(7.82+1.93)*1.2 -> 11.7 | J32: =(7.82+1.93)*1.22 -> 11.895 | K32: =K30-K31 -> 0 | M32: =SUM(B32:G32)-I32 -> 0.195
E33: =I33-C33-D33 -> 0 | F33: =I33-E33-D33 -> 0 | M33: =SUM(B33:G33)-I33 -> 0
E34: =I34-C34-D34 -> 0 | F34: =I34-E34-D34 -> 0 | M34: =SUM(B34:G34)-I34 -> 0
E35: =I35-C35-D35 -> 0 | F35: =I35-E35-D35 -> 0 | M35: =SUM(B35:G35)-I35 -> 0
A36: Строительно-монтажные работы | E36: 62089.599 | F36: =J36-E36 -> 154810.58 | H36: =173989.15+3797.88 -> 177787.03 | I36: =(173989.15+3797.88)*1.2 -> 213344.44 | J36: =(173989.15+3797.88)*1.22 -> 216900.18 | K36: =K32/1000 -> 0 | M36: =SUM(B36:G36)-I36 -> 3555.741 | O36: =Справка!U9 -> 0
A37: в том числе: | F37: =I37-E37-D37 -> 0 | M37: =SUM(B37:G37)-I37 -> 0
A38: Основные объекты строительства | F38: =I38-E38-D38 -> 632927.98 | I38: =527439.98*1.2 -> 632927.98 | J38: =527439.98*1.2 -> 632927.98 | M38: =SUM(B38:G38)-I38 -> 0
A39: Объекты энергетического хозяйства | F39: =I39-E39-D39 -> 63393.912 | I39: =52828.26*1.2 -> 63393.912 | J39: =52828.26*1.2 -> 63393.912 | M39: =SUM(B39:G39)-I39 -> 0
A40: Наружные сети и сооружения водоснабжения, водоотведения, теплоснабжения и газоснабжения | F40: =I40-E40-D40 -> 205335.3 | I40: =171112.75*1.2 -> 205335.3 | J40: =171112.75*1.2 -> 205335.3 | M40: =SUM(B40:G40)-I40 -> 0
A41: Благоустройство | F41: =I41-E41-D41 -> 2952.6 | I41: =2460.5*1.2 -> 2952.6 | J41: =2460.5*1.2 -> 2952.6 | M41: =SUM(B41:G41)-I41 -> 0
A42: Временные здания и сооружения | D42: =$L$42*(D36+D28) -> 0 | E42: =$L$42*(E36+E28) -> 0 | F42: =$L$42*(F36+F28) -> 0 | L42: =I42/(I36+I28) -> 0 | M42: =SUM(B42:G42)-I42 -> 0
A43: Прочие работы | B43: =SUM(B44:B46) -> 0 | D43: =SUM(D44:D46) -> 0 | E43: =SUM(E44:E46) -> 0 | F43: =SUM(F44:F46) -> 17727.21 | H43: =SUM(H44:H46) -> 14530.5 | I43: =SUM(I44:I46) -> 17436.6 | J43: =SUM(J44:J46) -> 17727.21 | K43: =Справка!AA15-Справка!W15-Справка!Y15 -> 0 | M43: =SUM(B43:G43)-I43 -> 290.61
A44: Перебазировка техники | F44: =J44-E44 -> 4126.674 | H44: 3382.52 | I44: =(3382.52)*1.2 -> 4059.024 | J44: =(3382.52)*1.22 -> 4126.674 | L44: =J44/($J$28+$J$36+$J$42) -> 0.017873186 | M44: =SUM(B44:G44)-I44 -> 67.65 | O44: =O31-O36 -> 20649782
A45: Доставка материалов | F45: =J45 -> 10186.366 | H45: =3629.08+4720.4 -> 8349.48 | I45: =(3629.08+4720.4)*1.2 -> 10019.376 | J45: =(3629.08+4720.4)*1.22 -> 10186.366 | L45: =J45/($J$28+$J$36+$J$42) -> 0.044118535 | M45: =SUM(B45:G45)-I45 -> 166.99
A46: Командировочные | F46: =J46 -> 3414.17 | H46: 2798.5 | I46: =(2798.5)*1.2 -> 3358.2 | J46: =(2798.5)*1.22 -> 3414.17 | L46: =J46/($J$28+$J$36+$J$42) -> 0.014787234 | M46: =SUM(B46:G46)-I46 -> 55.97
A47: Непредвиденные затраты: | B47: =SUM(B48:B49) -> 0 | D47: =SUM(D48:D49) -> 0 | E47: =SUM(E48:E49) -> 0 | F47: =F48+F49 -> 4972.271 | H47: =SUM(H48:H49) -> 4075.631 | I47: =SUM(I48:I49) -> 4890.757 | J47: =SUM(J48:J49) -> 4972.271 | L47: =Справка!AA19 -> 1.1445159e+08 | M47: =SUM(B47:G47)-I47 -> 81.514 | O47: 95583708
A48: Резерв на непредвиденные работы и затраты от СМР (1%) | F48: =J48 -> 4821.216 | H48: =(H30+H31+H45+H36)*2% -> 3951.816 | I48: =(I30+I31+I45+I36)*2% -> 4742.179 | J48: =(J30+J31+J45+J36)*2% -> 4821.216 | K48: =H48*1.2 -> 4742.179 | L48: =Справка!W15 -> 1.1445159e+08 | M48: =SUM(B48:G48)-I48 -> 79.037 | O48: =O47/Справка!F15/Справка!K165 -> #DIV/0!
A49: Резерв на непредвиденные работы и затраты от прочих затрат подрядчика (1%) | F49: =J49 -> 151.055 | H49: =(H46+H44+H32)*2% -> 123.815 | I49: =(I46+I44+I32)*2% -> 148.578 | J49: =(J46+J44+J32)*2% -> 151.055 | K49: =H49*1.2 -> 148.578 | M49: =SUM(B49:G49)-I49 -> 2.477
A50: - неиндексируемые | M50: =SUM(B50:G50)-I50 -> 0
A51: ВСЕГО | B51: =B26+B10 -> 12699.227 | D51: =D26+D10 -> 0 | E51: =E26+E10 -> 77623.348 | F51: =F26+F10 -> 185301.91 | G51: =G26+G10 -> 0 | H51: =H26+H10 -> 224344.06 | I51: =I26+I10 -> 267268.7 | J51: =J26+J10 -> 271528.19 | M51: =SUM(B51:G51)-I51 -> 8355.79
I52: 267268.69 | J52: =J51-K55 -> 0.004
I53: =I52-I51 -> -0.009 | K53: =224673790-10000000-1699250 -> 212974540
K54: =K53*1.22+10000000+1699250 -> 2.7152819e+08
K55: =K54/1000 -> 271528.19
E56: =J26*0.3 -> 76075.739 | F56: =J26-E56 -> 177510.06

Sheet НМЦК подряд
A1: СОГЛАСОВАНО | E1: УТВЕРЖДАЮ
A2: Заместитель начальника КГКУ "Камчатуправтодор" | E2: Начальник КГКУ "Камчатуправтодор"
A3: ______________А.Л. Нейштадт | E3: ______________О.В.Булах
A4: «____»______________2022 г. | E4: «____»______________2022 г.
A6: Расчет начальной (максимальной) цены контракта
A7: на строительство причальных сооружений через протоку Озерная в Усть-Камчатском районе Камчатского края
A9: Основания для расчета:
A10: 1. Приказ КГКУ "Камчатуправтодор" от 29.07.2022г. №402 Об утверждении проектной документации "Строительство причальных сооружений через протоку Озерная в Усть-Камчатском районе Камчатского края"
A11: 2. Положительное заключение государственной экспертизы проектной документации и результатов инженерных изысканий №41-1-1-2-049246-2022 от 22.07.2022г.
A12: 3. Утвержденный сводный сметный расчет
F13: руб.
A14: Наименование работ и затрат | B14: Стоимость работ в ценах на дату утверждения сметной документации на 2 квартал 2021 года | C14: Индекс фактической инфляции | D14: Стоимость работ в ценах на дату формирования начальной максимальной цены контракта | E14: Индекс прогнозной инфляции на период выполнения работ | F14: Начальная (максимальная) цена контракта с учетом индекса прогнозной инфляции на период выполнения работ
A15: 1 | B15: 2 | C15: 3 | D15: 4 | E15: 5 | F15: 6
A16: Подготовка территории строительства | B16: =Затраты!H28*1000-0.12 -> 11464050 | C16: =Справка!F15 -> 1.399 | D16: =B16*C16 -> 16038206 | E16: =Справка!K15 -> 1.07537 | F16: =ROUND(D16*E16,2) -> 17247005
A17: Строительно-монтажные работы | B17: =Затраты!I36/1.2*1000 -> 177787030 | C17: =$C$16 -> 1.399 | D17: =B17*C17 -> 2.4872405e+08 | E17: =$E$16 -> 1.07537 | F17: =ROUND(D17*E17,2) -> 2.6747039e+08
A18: Перебазировка техники | B18: =Затраты!I44/1.2*1000 -> 3382520 | C18: =$C$16 -> 1.399 | D18: =B18*C18 -> 4732145.5 | E18: =$E$16 -> 1.07537 | F18: =ROUND(D18*E18,2) -> 5088807.3
A19: Командировочные расходы | B19: =Затраты!I46/1.2*1000 -> 2798500 | C19: =$C$16 -> 1.399 | D19: =B19*C19 -> 3915101.5 | E19: =$E$16 -> 1.07537 | F19: =ROUND(D19*E19,2) -> 4210182.7
A20: Доставка основных материалов | B20: =Затраты!I45/1.2*1000 -> 8349480 | C20: =$C$16 -> 1.399 | D20: =B20*C20 -> 11680923 | E20: =$E$16 -> 1.07537 | F20: =ROUND(D20*E20,2) -> 12561314
A21: Резерв на непредвиденные работы и затраты 2% | B21: =(B16+B17+B18+B19+B20)*2% -> 4075631.6 | C21: =$C$16 -> 1.399 | D21: =B21*C21 -> 5701808.6 | E21: =$E$16 -> 1.07537 | F21: =ROUND(D21*E21,2) -> 6131553.9
A22: Стоимость СМР без учета НДС | B22: =SUM(B16:B21) -> 2.0785721e+08 | D22: =SUM(D16:D21) -> 2.9079224e+08 | F22: =SUM(F16:F21) -> 3.1270925e+08
A23: НДС (22%) | B23: =B22*0.22-0.01 -> 45728587 | D23: =D22*22% -> 63974293 | F23: =F22*22% -> 68796035
A24: Итого | B24: =B22+B23 -> 253585798 | D24: =D22+D23 -> 3.5476653e+08 | F24: =F22+F23 -> 3.8150528e+08
B25: =Справка!B14 -> 253585798 | D25: =Справка!H14 -> 354766531
A26: Продолжительность строительства: | B26: =B25-B24 -> 0 | D26: =B24*C22 -> 0 | F26: =Справка!AA14 -> 3.8150528e+08
A27: Начало производства работ - июнь 2026 года
A28: Окончание производства работ - октябрь 2027 года
A29: Уровень цен утвержденной сметной документации - 1 квартал 2022 года
A30: Дата формирования НМЦК - апрель 2026 года
A32: 1. Расчет индексов фактической инфляции с использованием ИПЦ Росстата (Камчатский край):
A34: =Справка!A24 -> март 2023 / март 2022 | B34: 108.6 | C34: =B34/100 -> 1.086
A35: =Справка!A25 -> март 2024 / март 2023 | B35: 109.53 | C35: =B35/100 -> 1.0953
A36: =Справка!A26 -> март 2025 / март 2024 | B36: 106.56 | C36: =B36/100 -> 1.0656
A37: =Справка!A27 -> 45748 | B37: 98.08 | C37: =B37/100 -> 0.9808
A38: =Справка!A28 -> 45778 | B38: 101.17 | C38: =B38/100 -> 1.0117
A39: =Справка!A29 -> 45809 | B39: 103.19 | C39: =B39/100 -> 1.0319
A40: =Справка!A30 -> 45839 | B40: 100.64 | C40: =B40/100 -> 1.0064
A41: =Справка!A31 -> 45870 | B41: 100.15 | C41: =B41/100 -> 1.0015
A42: =Справка!A32 -> 45901 | B42: 102.06 | C42: =B42/100 -> 1.0206
A43: =Справка!A33 -> 45931 | B43: 100.26 | C43: =B43/100 -> 1.0026
A44: =Справка!A34 -> 45962 | B44: 100.86 | C44: =B44/100 -> 1.0086
A45: =Справка!A35 -> 45992 | B45: 100.46 | C45: =B45/100 -> 1.0046
... A48: =Справка!A38 -> 46082 | B48: 100.99 | C48: =B48/100 -> 1.0099
A50: Индекс фактической инфляции | B50: =C34*C35*C36*C37*C38*C39*C40*C41*C42*C43*C44*C45*C46*C47*C48 -> 1.399
A52: 2. Расчет индекса прогнозной инфляции (Прогноз социально-экономического развития Камчатского края на 2023-2025 гг. (предварительный вариант) от 06.07.2022г., отрасль "Инвестиции в основной капитал"):
A57: 2026 = | B57: =Справка!F41 -> 1.078 | C57: Ежемесячный индекс прогноз на 2023 = | E57: 12√ | F57: =CONCATENATE(B57," = ",ROUND(B57^(1/12),4)) -> 1,078 = 1,0063
A60: 2027 = | B60: =Справка!F44 -> 1.077 | C60: Ежемесячный индекс прогноз на 2024 = | E60: 12√ | F60: =CONCATENATE(B60," = ",ROUND(B60^(1/12),4)) -> 1,077 = 1,0062
A63: Распределение стоимости подрядных работ по годам, рублей с учетом НДС 20% | B63: всего | C63: 2022 | D63: 2023 | E63: 2024
A64: Строительно-монтажные работы | B64: =B25 -> 253585798 | C64: =Затраты!D26*1000 -> 0 | D64: =Затраты!E26*1000 -> 76075739 | E64: =B64-C64-D64 -> 1.7751006e+08
A66: Доля сметной стоимости подлежащая выполнению подрядчиком в 2023 году | D66: =Справка!E46 -> 0.3
A67: Доля сметной стоимости подлежащая выполнению подрядчиком в 2024 году | D67: =Справка!E47 -> 0.7
A69: Ежемесячный прогнозный индекс
D70: степень | E70: период
A72: 2023 | B72: =Справка!C62 -> 1.0063 | C72: =POWER(B72,D72) -> 1.0063 | D72: =Справка!E62 -> 1 | E72: =Справка!F62 -> январь 2026
B73: =Справка!C63 -> 1.0063 | C73: =POWER(B73,D73) -> 1.05815 | D73: =Справка!E63 -> 9 | E73: =Справка!F63 -> апрель -декабрь 2026
A75: 2024 | B75: =Справка!C65 -> 1.0062 | C75: =POWER(B75,D75) -> 1.0062 | D75: =Справка!E65 -> 1 | E75: =Справка!F65 -> январь 2027
B76: =Справка!C66 -> 1.0062 | C76: =POWER(B76,D76) -> 1.06376 | D76: =Справка!E66 -> 10 | E76: =Справка!F66 -> январь-октябрь 2027
A78: 2026
A79: (1,00639-1) / 2+1 = | B79: =Справка!M52 -> 1.0291
A80: 2027
A81: 1,00639*((1,0062+1,006210) / 2) = | C81: =Справка!P54 -> 1.0952
A83: Индекс прогнозной инфляции
C84: =D66*B79+D67*C81 -> 1.07537
A86: Распределение НМЦК по годам:
B88: =Справка!U14 -> 0
A89: 2026 - | B89: =D64*B50*C84 -> 1.1445159e+08
A90: 2027 - | B90: =E64*B50*C84 -> 2.670537e+08
A92: Составил | B92: Заместитель начальника отдела строительства, реконструкции, капитального ремонта автомобильных дорог и сооружений на них | F92: О.А. Мельник
A93: Проверил | B93: Начальник отдела строительства, реконструкции, капитального ремонта автомобильных дорог и сооружений на них | F93: В.А. Кабаков
A94: Согласовал | B94: Заместитель начальника КГКУ "Камчатуправтодор" | F94: А.Л. Нейштадт

Sheet ССР 
D2: СВОДНЫЙ СМЕТНЫЙ РАСЧЕТ СТОИМОСТИ СТРОИТЕЛЬСТВА
C4: Строитсльство причальных сооружений через протоку Озерная в Усть-Камчатском районе Камчатского края
D5: (наименование стройки)
B7: Составлена в ценах по состоянию на 1 квартал 2022 г.
O8: =(H38)/(H25+H29+H16+H17+H18) -> 0.014787996 | P8: прочие общие
H9: Для расчета | O9: =(H37)/(H24+H28) -> 0.053245327 | P9: прочие левый
A10: № пп | B10: Номера сметных расчетов и смет | C10: Наименование глав, объектов, работ и затрат | D10: Сметная стоимость, тыс. руб. | H10: Общая сметная стоимость, тыс. руб. | I10: Доставка материалов | J10: Прочие | K10: Итого | L10: В ценах контракта | M10: Индекс перехода в цены контракта | O10: =(H36)/(H23+H27) -> 0.040715226 | P10: прочие правый
D11: строитель- ных работ | E11: монтажных работ | F11: оборудования, мебели, инвентаря | G11: прочих
A14: 1 | B14: 2 | C14: 3 | D14: 4 | E14: 5 | F14: 6 | G14: 7 | H14: 8
A15: Глава 1. Подготовка территории строительства
B16: 01-01 | C16: Демонтаж причальных сооружений. Правый берег | D16: 7693.11 | H16: =D16+E16+F16+G16 -> 7693.11 | J16: =H16*$O$8 -> 113.766 | K16: =H16+I16+J16 -> 7806.876 | L16: =K16*Справка!$F$15*Справка!$K$15 -> 11744.997 | M16: =L16/K16 -> 1.5044426
B17: 01-02 | C17: Демонтаж причальных сооружений. Левый берег | D17: 3264.51 | E17: 476.64 | H17: =D17+E17+F17+G17 -> 3741.15 | J17: =H17*$O$8 -> 55.324 | K17: =H17+I17+J17 -> 3796.474 | L17: =K17*Справка!$F$15*Справка!$K$15 -> 5711.577 | M17: =L17/K17 -> 1.5044425
B18: 01-03 | C18: Разборка существующих сооружений | D18: 20.04 | H18: =D18+E18+F18+G18 -> 20.04 | J18: =H18*$O$8 -> 0.296 | K18: =H18+I18+J18 -> 20.336 | L18: =K18*Справка!$F$15*Справка!$K$15 -> 30.594 | M18: =L18/K18 -> 1.5044256
B19: Расчет №1 | C19: Восстановление оси трассы (правый) | G19: 7.82 | H19: =D19+E19+F19+G19 -> 7.82 | K19: =H19+I19+J19 -> 7.82 | L19: =K19*Справка!$F$15*Справка!$K$15 -> 11.765 | M19: =L19/K19 -> 1.5044757
B20: Расчет №2 | C20: Восстановление оси трассы (левый) | G20: 1.93 | H20: =D20+E20+F20+G20 -> 1.93 | K20: =H20+I20+J20 -> 1.93 | L20: =K20*Справка!$F$15*Справка!$K$15 -> 2.904 | M20: =L20/K20 -> 1.5046632
B21: Итого по Главе 1. "Подготовка территории строительства" | D21: =SUM(D16:D20) -> 10977.66 | E21: =SUM(E16:E20) -> 476.64 | F21: =SUM(F16:F20) -> 0 | G21: =SUM(G16:G20) -> 9.75 | H21: =SUM(H16:H20) -> 11464.05 | I21: =SUM(I16:I20) -> 0 | J21: =SUM(J16:J20) -> 169.386 | K21: =SUM(K16:K20) -> 11633.436 | L21: =SUM(L16:L20) -> 17501.837
A22: Глава 2. Основные объекты строительства
B23: 02-01 | C23: Правый берег | D23: 86653.19 | E23: 23.94 | H23: =D23+E23+F23+G23 -> 86677.13 | I23: =H23*O10 -> 3529.079 | J23: =H23*$O$8 -> 1281.781 | K23: =H23+I23+J23 -> 91487.99 | L23: =K23*Справка!$F$15*Справка!$K$15 -> 137638.43 | M23: =L23/K23 -> 1.5044426
B24: 02-02 | C24: Левый берег | D24: 87288.08 | E24: 23.94 | H24: =D24+E24+F24+G24 -> 87312.02 | I24: =H24*O9 -> 4648.957 | J24: =H24*$O$8 -> 1291.17 | K24: =H24+I24+J24 -> 93252.147 | L24: =K24*Справка!$F$15*Справка!$K$15 -> 140292.51 | M24: =L24/K24 -> 1.5044426
B25: Итого по Главе 2. "Основные объекты строительства" | D25: =SUM(D23:D24) -> 173941.27 | E25: =SUM(E23:E24) -> 47.88 | F25: =SUM(F23:F24) -> 0 | G25: =SUM(G23:G24) -> 0 | H25: =SUM(H23:H24) -> 173989.15 | I25: =SUM(I23:I24) -> 8178.036 | J25: =SUM(J23:J24) -> 2572.951 | K25: =SUM(K23:K24) -> 184740.14 | L25: =SUM(L23:L24) -> 277930.94
A26: Глава 4. Объекты энергетического хозяйства
B27: 04-01 | C27: Наружное освещение (правый берег) | D27: 1627.57 | E27: 820.21 | F27: 8.33 | H27: =D27+E27+F27+G27 -> 2456.11 | I27: =H27*O10 -> 100.001 | J27: =H27*$O$8 -> 36.321 | K27: =H27+I27+J27 -> 2592.432 | L27: =K27*Справка!$F$15*Справка!$K$15 -> 3900.165 | M27: =L27/K27 -> 1.5044425
B28: 04-02 | C28: Наружное освещение (левый берег) | D28: 784.57 | E28: 550.82 | F28: 6.38 | H28: =D28+E28+F28+G28 -> 1341.77 | I28: =H28*O9 -> 71.443 | J28: =H28*$O$8 -> 19.842 | K28: =H28+I28+J28 -> 1433.055 | L28: =K28*Справка!$F$15*Справка!$K$15 -> 2155.949 | M28: =L28/K28 -> 1.5044426
B29: Итого по Главе 4. "Объекты энергетического хозяйства" | D29: =SUM(D27:D28) -> 2412.14 | E29: =SUM(E27:E28) -> 1371.03 | F29: =SUM(F27:F28) -> 14.71 | G29: =SUM(G27:G28) -> 0 | H29: =SUM(H27:H28) -> 3797.88 | I29: =SUM(I27:I28) -> 171.444 | J29: =SUM(J27:J28) -> 56.163 | K29: =SUM(K27:K28) -> 4025.487 | L29: =SUM(L27:L28) -> 6056.114
A30: Глава 7. Благоустройство и озеленение территории
B31: Итого по Главам 1-7 | D31: =D29+D25+D21 -> 187331.07 | E31: =E29+E25+E21 -> 1895.55 | F31: =F29+F25+F21 -> 14.71 | G31: =G29+G25+G21 -> 9.75 | H31: =H29+H25+H21 -> 189251.08 | I31: =I29+I25+I21 -> 8349.48 | J31: =J29+J25+J21 -> 2798.5 | K31: =K29+K25+K21 -> 200399.06 | L31: =L29+L25+L21 -> 301488.89
A32: Глава 8. Временные здания и сооружения
B33: Итого по Главам 1-8 | D33: =D31 -> 187331.07 | E33: =E31 -> 1895.55 | F33: =F31 -> 14.71 | G33: =G31 -> 9.75 | H33: =H31 -> 189251.08 | I33: =I31 -> 8349.48 | J33: =J31 -> 2798.5 | K33: =K31 -> 200399.06 | L33: =L31 -> 301488.89
A34: Глава 9. Прочие работы и затраты
B35: 09-01 | C35: Расчет перебазировки техники | G35: 3382.52 | H35: =D35+E35+F35+G35 -> 3382.52 | K35: =H35+I35+J35 -> 3382.52 | L35: =K35*Справка!$F$15*Справка!$K$15 -> 5088.807 | M35: =L35/K35 -> 1.5044425
B36: 09-02 | C36: Расчет стоимости доставки материалов (правый берег) | D36: 3629.08 | H36: =D36+E36+F36+G36 -> 3629.08
B37: 09-03 | C37: Расчет стоимости доставки материалов (левый берег) | D37: 4720.4 | H37: =D37+E37+F37+G37 -> 4720.4
B38: Расчет №3 | C38: Командировочные расходы | G38: 2798.5 | H38: =D38+E38+F38+G38 -> 2798.5
B39: Итого по Главе 9. "Прочие работы и затраты" | D39: =SUM(D35:D38) -> 8349.48 | E39: =SUM(E35:E38) -> 0 | F39: =SUM(F35:F38) -> 0 | G39: =SUM(G35:G38) -> 6181.02 | H39: =SUM(H35:H38) -> 14530.5 | I39: =SUM(I35:I38) -> 0 | J39: =SUM(J35:J38) -> 0 | K39: =SUM(K35:K38) -> 3382.52 | L39: =SUM(L35:L38) -> 5088.807
B40: Итого по Главам 1-9 | D40: =D39+D33 -> 195680.55 | E40: =E39+E33 -> 1895.55 | F40: =F39+F33 -> 14.71 | G40: =G39+G33 -> 6190.77 | H40: =H39+H33 -> 203781.58 | I40: =I39+I33 -> 8349.48 | J40: =J39+J33 -> 2798.5 | K40: =K39+K33 -> 203781.58 | L40: =L39+L33 -> 306577.7
I41: =H36+H37 -> 8349.48 | J41: =H38 -> 2798.5 | K41: =H40 -> 203781.58
C42: Непредвиденные затраты - 1% | H42: ='НМЦК подряд'!B21/1000 -> 4075.63 | K42: =H42+I42+J42 -> 4075.63 | L42: =K42*Справка!$F$15*Справка!$K$15 -> 6131.552
C43: НДС - 20% | H43: =(H40+H42)*20% -> 41571.44 | L43: =(L40+L42)*20% -> 62541.849
B44: Всего по сводному расчету | H44: =H40+H42+H43 -> 249428.65 | L44: =L40+L42+L43 -> 375251.1
H45: =Справка!B14/1000 -> 253585.8 | L45: =Справка!M14/1000 -> 381505.28

Sheet Расчеты 
A1: "Согласовано" | F1: "Утверждаю"
A2: Заместитель начальника КГКУ "Камчатуправтодор" | G2: Начальник КГКУ "Камчатуправтодор"
A3: ______________________Нейштадт А.Л. | G3: ______________________Булах О.В.
A5: Смета контракта
A7: =Справка!B5 -> Строительство причальных сооружений через протоку Озерная в Усть-Камчатском районе Камчатского края
L8: транспортировка, тн
A9: № п/п | B9: Номера сметных расчетов (смет) и подиций в сметных расчетах (сметах), относящиеся к соответсвующим конструктивным решениям (элементам), комплексам (видам) работ | C9: Наименование конструктивных решений (элементов), комплексов (видов) работ | D9: Ед. идм. | E9: Кол-во | F9: Единичная расценка, руб | G9: Общая стоимость, руб | L9: объем, левый берег | M9: объем, правый берег | N9: Цена за ед.
L10: 51.31 | M10: 88.421 | N10: =76.39*17.26+0.31*485*17.26 -> 3913.53 | Q10: Командировочные | R10: Перебазировка | S10: ИТОГО | T10: В ценах НМЦК | U10: =M10*N10 -> 346038.24
A11: 1 | B11: 2 | C11: 3 | D11: 4 | E11: 5 | F11: 6 | G11: 7 | L11: 568.18 | M11: 597.536 | N11: =76.39*17.26+0.31*511*17.26 -> 4052.65 | Q11: ='НМЦК подряд'!B16+'НМЦК подряд'!B17+'НМЦК подряд'!B20 -> 1.9760056e+08 | U11: =M11*N11 -> 2421604.3
A12: Глава 1. Подготовка территории строительства | L12: 4.73 | M12: 6.41 | N12: =76.39*17.26+0.31*511*17.26+2141.78*17.26 -> 41019.77 | Q12: =Q17/Q11 -> 0.014162409 | R12: =R17/Q11 -> 0.017117968 | U12: =M12*N12 -> 262936.73
A13: Раздел 1.1. Восстановление оси трассы
A14: 01.01.1 | B14: Расчет №1 | C14: Восстановление оси трассы (правый берег) | D14: км | E14: 0.335 | F14: =T14/E14 -> 36217.91 | G14: =F14*E14 -> 12133 | H14: =G14-T14 -> 0 | K14: 7820 | O14: =L14+M14+N14 -> 0 | P14: =K14 -> 7820 | Q14: =K14*$Q$12 -> 111 | R14: =K14*$R$12 -> 134 | S14: =P14+Q14+R14 -> 8065 | T14: =S14*'НМЦК подряд'!$C$16*'НМЦК подряд'!$E$16 -> 12133
A15: 01.01.2 | B15: Расчет №2 | C15: Восстановление оси трассы (левый берег) | D15: км | E15: 0.9 | F15: =T15/E15 -> 3326.67 | G15: =F15*E15 -> 2994 | K15: 1930 | O15: =L15+M15+N15 -> 0 | P15: =K15 -> 1930 | Q15: =K15*$Q$12 -> 27 | R15: =K15*$R$12 -> 33 | S15: =P15+Q15+R15 -> 1990 | T15: =S15*'НМЦК подряд'!$C$16*'НМЦК подряд'!$E$16 -> 2994
C16: Итого: раздел 1.1. | G16: =SUM(G14:G15) -> 15127 | K16: =K14+K15 -> 9750 | L16: =L14+L15 -> 0 | M16: =M14+M15 -> 0 | N16: =N14+N15 -> 0 | O16: =O14+O15 -> 0 | P16: =P14+P15 -> 9750 | Q16: =Q14+Q15 -> 138 | R16: =R14+R15 -> 167 | ... U16: =U14+U15 -> 0
A17: Раздел 1.2. Демонтаж конструкций причального сооружения. Правый берег | L17: 96 | M17: 96 | N17: =76.39*17.26+0.31*524*17.26 -> 4122.21 | Q17: ='НМЦК подряд'!B19 -> 2798500 | R17: ='НМЦК подряд'!B18 -> 3382520 | U17: =M17*N17 -> 395732.16
A18: 01.02.1 | B18: ЛСР №01-01, п.1-6 | C18: Демонтаж существующего деревянного причала (правый берег) с погрузкой и транспортировкой на расстояние до 9 км | D18: комплекс | E18: 1 | F18: =T18/E18 -> 5650864 | G18: =F18*E18 -> 5650864 | K18: =2379956+55156+491806+681965+7945+25361 -> 3642189 | O18: =L18+M18+N18 -> 0 | P18: =K18 -> 3642189 | Q18: =K18*$Q$12 -> 51582 | R18: =K18*$R$12 -> 62347 | S18: =P18+Q18+R18 -> 3756118 | T18: =S18*'НМЦК подряд'!$C$16*'НМЦК подряд'!$E$16 -> 5650864
A19: 01.02.2 | B19: ЛСР №01-01, п.7-12 | C19: Демонтаж существующего пирса (правый берег) с погрузкой и транспортировкой на расстояние до 9 км | D19: комплекс | E19: 1 | F19: =T19/E19 -> 6285005 | G19: =F19*E19 -> 6285005 | K19: =1411337+60887+175490+2336974+15798+50430 -> 4050916 | O19: =L19+M19+N19 -> 0 | P19: =K19 -> 4050916 | Q19: =K19*$Q$12 -> 57371 | R19: =K19*$R$12 -> 69343 | S19: =P19+Q19+R19 -> 4177630 | T19: =S19*'НМЦК подряд'!$C$16*'НМЦК подряд'!$E$16 -> 6285005
C20: Итого: раздел 1.2. | G20: =SUM(G18:G19) -> 11935869 | K20: =SUM(K18:K19) -> 7693105 | L20: =SUM(L18:L19) -> 0 | M20: =SUM(M18:M19) -> 0 | N20: =SUM(N18:N19) -> 0 | O20: =SUM(O18:O19) -> 0 | P20: =SUM(P18:P19) -> 7693105 | Q20: =SUM(Q18:Q19) -> 108953 | R20: =SUM(R18:R19) -> 131690 | ... U20: =SUM(U18:U19) -> 0
A21: Раздел 1.3. Демонтаж конструкций причала левого берега. | O21: =L21+M21+N21 -> 0
A22: Раздел 1.3.1 Временный пирс (судно-лихтер) | O22: =L22+M22+N22 -> 0
A23: 01.03.1 | B23: ЛСР №01-02 п.1 | C23: Срезка надстроек, возвышающихся над уровнем воды | D23: м | E23: 750 | F23: =T23/E23 -> 871.52 | G23: =E23*F23 -> 653640 | K23: 421295 | O23: =L23+M23+N23 -> 0 | P23: =K23+L23+M23+N23 -> 421295 | Q23: =P23*$Q$12 -> 5967 | R23: =P23*$R$12 -> 7212 | S23: =P23+Q23+R23 -> 434474 | T23: =S23*'НМЦК подряд'!$C$16*'НМЦК подряд'!$E$16 -> 653641
A24: 01.03.2 | B24: ЛСР №01-02 п.2 | C24: Откачка воды из корпуса судна-лихтера передвижным насосом | D24: м3 | E24: 100 | F24: =T24/E24 -> 140.15 | G24: =E24*F24 -> 14015 | K24: 9033 | O24: =L24+M24+N24 -> 0 | P24: =K24+L24+M24+N24 -> 9033 | Q24: =P24*$Q$12 -> 128 | R24: =P24*$R$12 -> 155 | S24: =P24+Q24+R24 -> 9316 | T24: =S24*'НМЦК подряд'!$C$16*'НМЦК подряд'!$E$16 -> 14015
A25: 01.03.3 | B25: ЛСР №01-02 п.3 | C25: Очистка трюма судна-лихтера от грунта | D25: м3 | E25: 100 | F25: =T25/E25 -> 228.57 | G25: =E25*F25 -> 22857 | K25: 14732 | O25: =L25+M25+N25 -> 0 | P25: =K25+L25+M25+N25 -> 14732 | Q25: =P25*$Q$12 -> 209 | R25: =P25*$R$12 -> 252 | S25: =P25+Q25+R25 -> 15193 | T25: =S25*'НМЦК подряд'!$C$16*'НМЦК подряд'!$E$16 -> 22857
A26: 01.03.4 | B26: ЛСР №01-02 п.4 | C26: Выравнивание берега до пляжного откоса | D26: м3 | E26: 200 | F26: =T26/E26 -> 39.77 | G26: =E26*F26 -> 7954 | K26: 5126 | O26: =L26+M26+N26 -> 0 | P26: =K26+L26+M26+N26 -> 5126 | Q26: =P26*$Q$12 -> 73 | R26: =P26*$R$12 -> 88 | S26: =P26+Q26+R26 -> 5287 | T26: =S26*'НМЦК подряд'!$C$16*'НМЦК подряд'!$E$16 -> 7954
A27: 01.03.5 | B27: ЛСР №01-02 п.5, п.6 | C27: Забивка свай фундамента анкерной опоры | D27: т | E27: 6.57 | F27: =T27/E27 -> 171729.98 | G27: =E27*F27 -> 1128266 | K27: =94460+632749 -> 727209 | O27: =L27+M27+N27 -> 0 | P27: =K27+L27+M27+N27 -> 727209 | Q27: =P27*$Q$12 -> 10299 | R27: =P27*$R$12 -> 12448 | S27: =P27+Q27+R27 -> 749956 | T27: =S27*'НМЦК подряд'!$C$16*'НМЦК подряд'!$E$16 -> 1128266
A28: 01.03.6 | B28: ЛСР №01-02 п.7-9 | C28: Монтаж анкерной опоры в виде ростверка | D28: м3 | E28: 12 | F28: =T28/E28 -> 28581.75 | G28: =E28*F28 -> 342981 | K28: =86744+129727+4593 -> 221064 | O28: =L28+M28+N28 -> 0 | P28: =K28+L28+M28+N28 -> 221064 | Q28: =P28*$Q$12 -> 3131 | R28: =P28*$R$12 -> 3784 | S28: =P28+Q28+R28 -> 227979 | T28: =S28*'НМЦК подряд'!$C$16*'НМЦК подряд'!$E$16 -> 342981
A29: 01.03.7 | B29: ЛСР №01-02 п.10 | C29: Откачка воды из трюма лихтера | D29: м3 | E29: 200 | F29: =T29/E29 -> 140.13 | G29: =E29*F29 -> 28026 | K29: =18064 -> 18064 | O29: =L29+M29+N29 -> 0 | P29: =K29+L29+M29+N29 -> 18064 | Q29: =P29*$Q$12 -> 256 | R29: =P29*$R$12 -> 309 | S29: =P29+Q29+R29 -> 18629 | T29: =S29*'НМЦК подряд'!$C$16*'НМЦК подряд'!$E$16 -> 28026
A30: 01.03.8 | B30: ЛСР №01-02 п.11-12 | C30: Вытаскивание корпуса судна-лихтера на берег | D30: т | E30: 100 | F30: =T30/E30 -> 8086.47 | G30: =E30*F30 -> 808647 | K30: =512711+8492 -> 521203 | O30: =L30+M30+N30 -> 0 | P30: =K30+L30+M30+N30 -> 521203 | Q30: =P30*$Q$12 -> 7381 | R30: =P30*$R$12 -> 8922 | S30: =P30+Q30+R30 -> 537506 | T30: =S30*'НМЦК подряд'!$C$16*'НМЦК подряд'!$E$16 -> 808647
A31: 01.03.10 | B31: ЛСР №01-02 п.13 | C31: Демонтаж анкерных опор в виде ростверка | D31: м3 | E31: 12 | F31: =T31/E31 -> 146671.75 | G31: =E31*F31 -> 1760061 | K31: 1134424 | O31: =L31+M31+N31 -> 0 | P31: =K31+L31+M31+N31 -> 1134424 | Q31: =P31*$Q$12 -> 16066 | R31: =P31*$R$12 -> 19419 | S31: =P31+Q31+R31 -> 1169909 | T31: =S31*'НМЦК подряд'!$C$16*'НМЦК подряд'!$E$16 -> 1760061
A32: 01.03.11 | B32: ЛСР №01-02 п.14 | C32: Демонтаж свай | D32: т | E32: 6.57 | F32: =T32/E32 -> 27220.55 | G32: =E32*F32 -> 178839.01 | K32: 115269 | O32: =L32+M32+N32 -> 0 | P32: =K32+L32+M32+N32 -> 115269 | Q32: =P32*$Q$12 -> 1632 | R32: =P32*$R$12 -> 1973 | S32: =P32+Q32+R32 -> 118874 | T32: =S32*'НМЦК подряд'!$C$16*'НМЦК подряд'!$E$16 -> 178839
A33: 01.03.12 | B33: ЛСР №01-02 п.15 | C33: Перевозка автосамосвалами металлолома на расстояние до 10 км | D33: т | E33: 150 | F33: =T33/E33 -> 280.38 | G33: =E33*F33 -> 42057 | K33: 27107 | O33: =L33+M33+N33 -> 0 | P33: =K33+L33+M33+N33 -> 27107 | Q33: =P33*$Q$12 -> 384 | R33: =P33*$R$12 -> 464 | S33: =P33+Q33+R33 -> 27955 | T33: =S33*'НМЦК подряд'!$C$16*'НМЦК подряд'!$E$16 -> 42057
C34: Итого по Разделу 1.3.1 | G34: =SUM(G23:G33) -> 4987343 | K34: =SUM(K23:K33) -> 3214526 | L34: =SUM(L23:L33) -> 0 | M34: =SUM(M23:M33) -> 0 | N34: =SUM(N23:N33) -> 0 | O34: =SUM(O23:O33) -> 0 | P34: =SUM(P23:P33) -> 3214526 | Q34: =SUM(Q23:Q33) -> 45526 | R34: =SUM(R23:R33) -> 55026 | ... U34: =SUM(U23:U33) -> 0
A35: Раздел 1.3.2 Временный причал (плашкоут) | O35: =L35+M35+N35 -> 0 | P35: =K35+L35+M35+N35 -> 0 | Q35: =P35*$Q$12 -> 0 | R35: =P35*$R$12 -> 0 | S35: =K35+Q35+R35 -> 0 | T35: =S35*'НМЦК подряд'!$C$16*'НМЦК подряд'!$E$16 -> 0
A36: 14 | B36: ЛСР №01-02 п.16 | C36: Очистка корпуса плашкоута от грунта экскаватором | D36: м3 | E36: 200 | F36: =T36/E36 -> 157.66 | G36: =E36*F36 -> 31532 | K36: 20323 | O36: =L36+M36+N36 -> 0 | P36: =K36+L36+M36+N36 -> 20323 | Q36: =P36*$Q$12 -> 288 | R36: =P36*$R$12 -> 348 | S36: =P36+Q36+R36 -> 20959 | T36: =S36*'НМЦК подряд'!$C$16*'НМЦК подряд'!$E$16 -> 31532
A37: 01.03.13 | B37: ЛСР №01-02 п.17 | C37: Откачка воды из корпуса плашкоута насосами | D37: т | E37: 100 | F37: =T37/E37 -> 140.15 | G37: =E37*F37 -> 14015 | K37: 9033 | O37: =L37+M37+N37 -> 0 | P37: =K37+L37+M37+N37 -> 9033 | Q37: =P37*$Q$12 -> 128 | R37: =P37*$R$12 -> 155 | S37: =P37+Q37+R37 -> 9316 | T37: =S37*'НМЦК подряд'!$C$16*'НМЦК подряд'!$E$16 -> 14015
A38: 01.03.14 | B38: ЛСР №01-02 п.18-19 | C38: Вытаскивание корпуса плашкоута на берег | D38: т | E38: 50 | F38: =T38/E38 -> 14942.1 | G38: =E38*F38 -> 747105 | K38: =476635+4901 -> 481536 | O38: =L38+M38+N38 -> 0 | P38: =K38+L38+M38+N38 -> 481536 | Q38: =P38*$Q$12 -> 6820 | R38: =P38*$R$12 -> 8243 | S38: =P38+Q38+R38 -> 496599 | T38: =S38*'НМЦК подряд'!$C$16*'НМЦК подряд'!$E$16 -> 747105
A39: 01.03.15 | B39: ЛСР №01-02 п.20 | C39: Перевозка автосамосвалами металлолома на расстояние до 10 км | D39: т | E39: 87 | F39: =T39/E39 -> 280.38 | G39: =E39*F39 -> 24393.06 | K39: =15722 -> 15722 | O39: =L39+M39+N39 -> 0 | P39: =K39+L39+M39+N39 -> 15722 | Q39: =P39*$Q$12 -> 223 | R39: =P39*$R$12 -> 269 | S39: =P39+Q39+R39 -> 16214 | T39: =S39*'НМЦК подряд'!$C$16*'НМЦК подряд'!$E$16 -> 24393
C40: Итого по Разделу 1.3.2 | G40: =SUM(G36:G39) -> 817045.06 | K40: =SUM(K36:K39) -> 526614 | L40: =SUM(L36:L39) -> 0 | M40: =SUM(M36:M39) -> 0 | N40: =SUM(N36:N39) -> 0 | O40: =L40+M40+N40 -> 0 | P40: =SUM(P36:P39) -> 526614 | Q40: =SUM(Q36:Q39) -> 7459 | R40: =SUM(R36:R39) -> 9015 | S40: =P40+Q40+R40 -> 543088 | T40: =SUM(T36:T39) -> 817045
C41: Итого по Разделу 1.3. | G41: =G40+G34 -> 5804388 | K41: =K40+K34 -> 3741140 | L41: =L40+L34 -> 0 | M41: =M40+M34 -> 0 | N41: =N40+N34 -> 0 | O41: =O40+O34 -> 0 | P41: =P40+P34 -> 3741140 | Q41: =Q40+Q34 -> 52985 | R41: =R40+R34 -> 64041 | ... U41: =U40+U34 -> 0
A42: Раздел 1.4. Демонтаж существущего обустройства | O42: =L42+M42+N42 -> 0 | P42: =K42+L42+M42+N42 -> 0 | Q42: =P42*$Q$12 -> 0 | R42: =P42*$R$12 -> 0 | S42: =K42+Q42+R42 -> 0 | T42: =S42*'НМЦК подряд'!$C$16*'НМЦК подряд'!$E$16 -> 0
A43: 01.04.1 | B43: ЛСР №01-03, п.1-2 | C43: Демонтаж дорожных знаков на металлических стойках с транспортировкой на полигон ТБО на расстояние до 9 км | D43: шт | E43: 4 | F43: =T43/E43 -> 7771.5 | G43: =F43*E43 -> 31086 | K43: 20036 | O43: =L43+M43+N43 -> 0 | P43: =K43+L43+M43+N43 -> 20036 | Q43: =P43*$Q$12 -> 284 | R43: =P43*$R$12 -> 343 | S43: =P43+Q43+R43 -> 20663 | T43: =S43*'НМЦК подряд'!$C$16*'НМЦК подряд'!$E$16 -> 31086
C44: Итого: раздел 1.4. | G44: =G43 -> 31086 | K44: =SUM(K42:K43) -> 20036 | L44: =SUM(L42:L43) -> 0 | M44: =SUM(M42:M43) -> 0 | N44: =SUM(N42:N43) -> 0 | O44: =SUM(O42:O43) -> 0 | P44: =SUM(P42:P43) -> 20036 | Q44: =SUM(Q42:Q43) -> 284 | R44: =SUM(R42:R43) -> 343 | ... U44: =SUM(U42:U43) -> 0
C45: Итого: Глава 1. | G45: =G44+G41+G20+G16 -> 17786470 | K45: =K44+K41+K20+K16 -> 11464031 | L45: =L44+L41+L20+L16 -> 0 | M45: =M44+M41+M20+M16 -> 0 | N45: =N44+N41+N20+N16 -> 0 | O45: =O44+O41+O20+O16 -> 0 | P45: =P44+P41+P20+P16 -> 11464031 | Q45: =Q44+Q41+Q20+Q16 -> 162360 | R45: =R44+R41+R20+R16 -> 196241 | ... U45: =U44+U41+U20+U16 -> 0
A46: Глава 2. Причальное сооружение (правый берег) | O46: =L46+M46+N46 -> 0 | P46: =K46+L46+M46+N46 -> 0 | Q46: =P46*$Q$12 -> 0 | R46: =P46*$R$12 -> 0 | S46: =K46+Q46+R46 -> 0 | T46: =S46*'НМЦК подряд'!$C$16*'НМЦК подряд'!$E$16 -> 0
A47: Раздел 2.1. Конструктивные элементы (правый берег) | O47: =L47+M47+N47 -> 0 | P47: =K47+L47+M47+N47 -> 0 | Q47: =P47*$Q$12 -> 0 | R47: =P47*$R$12 -> 0 | S47: =K47+Q47+R47 -> 0 | T47: =S47*'НМЦК подряд'!$C$16*'НМЦК подряд'!$E$16 -> 0
C48: Причал
A49: 02.01.1 | B49: ЛСР №02-01-01, п. 1 | C49: Погружение вертикальных свай С-1 | D49: тн | E49: 23.81 | F49: =T49/E49 -> 64335.95 | G49: =F49*E49 -> 1531839 | K49: =4169080/100.54*23.81 -> 987326 | O49: =L49+M49+N49 -> 0 | P49: =K49+L49+M49+N49 -> 987326 | Q49: =P49*$Q$12 -> 13983 | R49: =P49*$R$12 -> 16901 | S49: =P49+Q49+R49 -> 1018210 | T49: =S49*'НМЦК подряд'!$C$16*'НМЦК подряд'!$E$16 -> 1531839 | U49: =SUM(L49:N49) -> 0
A50: 02.01.2 | B50: ЛСР №02-01-01, п. 1 | C50: Погружение вертикальных свай С-2 | D50: тн | E50: 76.73 | F50: =T50/E50 -> 64335.96 | G50: =F50*E50 -> 4936498.2 | K50: =4169080/100.54*76.73 -> 3181754 | O50: =L50+M50+N50 -> 0 | P50: =K50+L50+M50+N50 -> 3181754 | Q50: =P50*$Q$12 -> 45061 | R50: =P50*$R$12 -> 54465 | S50: =P50+Q50+R50 -> 3281280 | T50: =S50*'НМЦК подряд'!$C$16*'НМЦК подряд'!$E$16 -> 4936498 | U50: =L50+M50+N50 -> 0
A51: 02.01.3 | B51: ЛСР №02-01-01, п. 2 | C51: Погружение наклонных свай С-3 | D51: тн | E51: 76.73 | F51: =T51/E51 -> 77839.31 | G51: =F51*E51 -> 5972610.3 | K51: =3849566 -> 3849566 | O51: =L51+M51+N51 -> 0 | P51: =K51+L51+M51+N51 -> 3849566 | Q51: =P51*$Q$12 -> 54519 | R51: =P51*$R$12 -> 65897 | S51: =P51+Q51+R51 -> 3969982 | T51: =S51*'НМЦК подряд'!$C$16*'НМЦК подряд'!$E$16 -> 5972610 | U51: =L51+M51+N51 -> 0
A52: 02.01.4 | B52: ЛСР №02-01-01, п. 3, ЛСР 09-02-01 п. 1 | C52: Сваи из стальных труб d=630 мм, толщина стенки 12 мм | D52: тн | E52: 179 | F52: =T52/E52 -> 154224.96 | G52: =F52*E52 -> 27606268 | K52: 17067827 | L52: =179*N11 -> 725424 | O52: =L52+M52+N52 -> 725424 | P52: =K52+L52+M52+N52 -> 17793251 | Q52: =P52*$Q$12 -> 251995 | R52: =P52*$R$12 -> 304584 | S52: =P52+Q52+R52 -> 18349830 | T52: =S52*'НМЦК подряд'!$C$16*'НМЦК подряд'!$E$16 -> 27606267 | U52: =L52+M52+N52 -> 725424
A53: 02.01.5 | B53: ЛСР №02-01-01, п. 6 | C53: Установка арматурного каркаса | D53: шт | E53: 67 | F53: =T53/E53 -> 30016.82 | G53: =F53*E53 -> 2011126.9 | K53: =1296245 -> 1296245 | O53: =L53+M53+N53 -> 0 | P53: =K53+L53+M53+N53 -> 1296245 | Q53: =P53*$Q$12 -> 18358 | R53: =P53*$R$12 -> 22189 | S53: =P53+Q53+R53 -> 1336792 | T53: =S53*'НМЦК подряд'!$C$16*'НМЦК подряд'!$E$16 -> 2011127
A54: 02.01.6 | B54: ЛСР №02-01-01, п. 7, ЛСР 09-02-01 п. 1 | C54: Арматурные каркасы | D54: тн | E54: 19.27 | F54: =T54/E54 -> 173941.62 | G54: =F54*E54 -> 3351855 | K54: 2090525 | M54: =17.24*N11 -> 69868 | O54: =L54+M54+N54 -> 69868 | P54: =K54+L54+M54+N54 -> 2160393 | Q54: =P54*$Q$12 -> 30596 | R54: =P54*$R$12 -> 36982 | S54: =P54+Q54+R54 -> 2227971 | T54: =S54*'НМЦК подряд'!$C$16*'НМЦК подряд'!$E$16 -> 3351855 | U54: =L54+M54+N54 -> 69868
A55: 02.01.7 | B55: ЛСР №02-01-01, п. 8-10, ЛСР 09-02-01 п. 1 | C55: Заполнение свай бетоном | D55: м3 | E55: 155.44 | F55: =T55/E55 -> 45412.91 | G55: =F55*E55 -> 7058982.7 | K55: =2691400+1521739+67333 -> 4280472 | N55: =155.44*0.4275*N11 -> 269301 | O55: =L55+M55+N55 -> 269301 | P55: =K55+L55+M55+N55 -> 4549773 | Q55: =P55*$Q$12 -> 64436 | R55: =P55*$R$12 -> 77883 | S55: =P55+Q55+R55 -> 4692092 | T55: =S55*'НМЦК подряд'!$C$16*'НМЦК подряд'!$E$16 -> 7058983 | U55: =L55+M55+N55 -> 269301
A56: 02.01.8 | B56: ЛСР №02-01-01, п. 4-5, ЛСР 09-02-01 п. 1 | C56: Погружение шпунтов | D56: тн | E56: 59.7 | F56: =T56/E56 -> 236099.7 | G56: =F56*E56 -> 14095152 | K56: =3480452+5362447 -> 8842899 | L56: =59.7*N11 -> 241943 | O56: =L56+M56+N56 -> 241943 | P56: =K56+L56+M56+N56 -> 9084842 | Q56: =P56*$Q$12 -> 128663 | R56: =P56*$R$12 -> 155514 | S56: =P56+Q56+R56 -> 9369019 | T56: =S56*'НМЦК подряд'!$C$16*'НМЦК подряд'!$E$16 -> 14095152 | U56: =L56+M56+N56 -> 241943
A57: 02.01.9 | B57: ЛСР №02-01-01, п. 43-46 | C57: Нанесение вручную праймера на стальную надвобную поверхность сваи (шпунта) | D57: м2 | E57: =201+165 -> 366 | F57: =T57/E57 -> 668.95 | G57: =F57*E57 -> 244835.7 | K57: =(41384-937-27325+144684)/183*100.5+71142 -> 157806 | O57: =L57+M57+N57 -> 0 | P57: =K57+L57+M57+N57 -> 157806 | Q57: =P57*$Q$12 -> 2235 | R57: =P57*$R$12 -> 2701 | S57: =P57+Q57+R57 -> 162742 | T57: =S57*'НМЦК подряд'!$C$16*'НМЦК подряд'!$E$16 -> 244836 | U57: =L57+M57+N57 -> 0
A58: 02.01.11 | B58: ЛСР №02-01-01, п. 47-48 | C58: Нанесение обматыванием по спирали ленты на надводную поверхность стальной сваи | D58: м2 | E58: =126+113 -> 239 | F58: =T58/E58 -> 20854.92 | G58: =F58*E58 -> 4984325.9 | K58: =(79191+3133389)/239*126+1518919 -> 3212580 | O58: =L58+M58+N58 -> 0 | P58: =K58+L58+M58+N58 -> 3212580 | Q58: =P58*$Q$12 -> 45498 | R58: =P58*$R$12 -> 54993 | S58: =P58+Q58+R58 -> 3313071 | T58: =S58*'НМЦК подряд'!$C$16*'НМЦК подряд'!$E$16 -> 4984325 | U58: =L58+M58+N58 -> 0
A59: 02.01.13 | B59: ЛСР №02-01-01, п. 49-50 | C59: Монтаж кожуха на надводную поверхность стальной сваи | D59: м2 | E59: =126+113 -> 239 | F59: =T59/E59 -> 6436.7 | G59: =F59*E59 -> 1538371.3 | K59: =(839768+151768)/239*126+468802 -> 991536 | O59: =L59+M59+N59 -> 0 | P59: =K59+L59+M59+N59 -> 991536 | Q59: =P59*$Q$12 -> 14043 | R59: =P59*$R$12 -> 16973 | S59: =P59+Q59+R59 -> 1022552 | T59: =S59*'НМЦК подряд'!$C$16*'НМЦК подряд'!$E$16 -> 1538371 | U59: =L59+M59+N59 -> 0
A60: 02.01.15 | B60: ЛСР №02-01-01, п. 51 | C60: Нанесение мастики на подготовленную стальную поверхность над водой | D60: м2 | E60: 108.2 | F60: =T60/E60 -> 1524.43 | G60: =F60*E60 -> 164943.33 | K60: =106311/108.2*100.2+7860 -> 106311 | O60: =L60+M60+N60 -> 0 | P60: =K60+L60+M60+N60 -> 106311 | Q60: =P60*$Q$12 -> 1506 | R60: =P60*$R$12 -> 1820 | S60: =P60+Q60+R60 -> 109637 | T60: =S60*'НМЦК подряд'!$C$16*'НМЦК подряд'!$E$16 -> 164943 | U60: =L60+M60+N60 -> 0
A61: 02.01.17 | B61: ЛСР №02-01-01, п. 11, ЛСР 09-02-01 п. 1 | C61: Устройство наголовника свай НС-1, НС-2, НС-3 | D61: тн | E61: =1.67+0.9+0.24 -> 2.81 | F61: =T61/E61 -> 321893.59 | G61: =F61*E61 -> 904520.99 | K61: 571608 | M61: =2.81*$N$11 -> 11388 | O61: =L61+M61+N61 -> 11388 | P61: =K61+L61+M61+N61 -> 582996 | Q61: =P61*$Q$12 -> 8257 | R61: =P61*$R$12 -> 9980 | S61: =P61+Q61+R61 -> 601233 | T61: =S61*'НМЦК подряд'!$C$16*'НМЦК подряд'!$E$16 -> 904521 | U61: =L61+M61+N61 -> 11388
A62: 02.01.18 | B62: ЛСР №02-01-01, п. 12-13, ЛСР 09-02-01 п. 1 | C62: Устройство связи СВ-1, СВ-2, СВ-3 на причале (стальная конструкция) | D62: тн | E62: 4.6328 | F62: =T62/E62 -> 289602.83 | G62: =F62*E62 -> 1341672 | K62: =356964+489110 -> 846074 | L62: =(2.45+1.06+1.1)*$N$11 -> 18683 | O62: =L62+M62+N62 -> 18683 | P62: =K62+L62+M62+N62 -> 864757 | Q62: =P62*$Q$12 -> 12247 | R62: =P62*$R$12 -> 14803 | S62: =P62+Q62+R62 -> 891807 | T62: =S62*'НМЦК подряд'!$C$16*'НМЦК подряд'!$E$16 -> 1341672 | U62: =L62+M62+N62 -> 18683
C63: Возведение верхнего строения пирса | U63: =L63+M63+N63 -> 0
A64: 02.01.19 | B64: ЛСР №02-01-01, п. 52-53, ЛСР 09-02-01 п. 1 | C64: Устройство связи СВ-1, СВ-4, СВ-5 на пирсе (стальная конструкция) | D64: тн | E64: 6.0149 | F64: =T64/E64 -> 289969.74 | G64: =F64*E64 -> 1744139 | K64: =463443+635025 -> 1098468 | L64: =(3.7+1.4+1.24)*$N$11 -> 25694 | O64: =L64+M64+N64 -> 25694 | P64: =K64+L64+M64+N64 -> 1124162 | Q64: =P64*$Q$12 -> 15921 | R64: =P64*$R$12 -> 19243 | S64: =P64+Q64+R64 -> 1159326 | T64: =S64*'НМЦК подряд'!$C$16*'НМЦК подряд'!$E$16 -> 1744139 | U64: =L64+M64+N64 -> 25694
A65: 02.01.20 | B65: ЛСР №02-01-01, п. 61-63, ЛСР 09-02-01 п. 1 | C65: Омоноличивание оголовока пирса | D65: м3 | E65: 16 | F65: =T65/E65 -> 50045.13 | G65: =F65*E65 -> 800722.08 | K65: =312632+169736+6007 -> 488375 | N65: =E65*0.4275*N11 -> 27720 | O65: =L65+M65+N65 -> 27720 | P65: =K65+L65+M65+N65 -> 516095 | Q65: =P65*$Q$12 -> 7309 | R65: =P65*$R$12 -> 8834 | S65: =P65+Q65+R65 -> 532238 | T65: =S65*'НМЦК подряд'!$C$16*'НМЦК подряд'!$E$16 -> 800722 | U65: =L65+M65+N65 -> 27720
A66: 02.01.21 | B66: ЛСР №02-01-01, п. 72 | C66: Устройство антисейсмических швов | D66: м | E66: 5.2 | F66: =T66/E66 -> 3214.23 | G66: =F66*E66 -> 16714 | K66: 10773 | O66: =L66+M66+N66 -> 0 | P66: =K66+L66+M66+N66 -> 10773 | Q66: =P66*$Q$12 -> 153 | R66: =P66*$R$12 -> 184 | S66: =P66+Q66+R66 -> 11110 | T66: =S66*'НМЦК подряд'!$C$16*'НМЦК подряд'!$E$16 -> 16714 | U66: =L66+M66+N66 -> 0
A67: 02.01.22 | B67: ЛСР №02-01-01, п. 64, ЛСР 09-02-01 п. 1 | C67: Армирование оголовка пирса | D67: т | E67: =2.5+1.4+0.14 -> 4.04 | F67: =T67/E67 -> 154077.72 | G67: =F67*E67 -> 622473.99 | K67: =384834 -> 384834 | M67: =E67*$N$11 -> 16373 | O67: =L67+M67+N67 -> 16373 | P67: =K67+L67+M67+N67 -> 401207 | Q67: =P67*$Q$12 -> 5682 | R67: =P67*$R$12 -> 6868 | S67: =P67+Q67+R67 -> 413757 | T67: =S67*'НМЦК подряд'!$C$16*'НМЦК подряд'!$E$16 -> 622474 | U67: =L67+M67+N67 -> 16373
A68: 02.01.23 | B68: ЛСР №02-01-01, п. 56, | C68: Монтаж каркаса поддерживающего КП-1 из арматуры | D68: т | E68: 0,46 | F68: =T68/E68 -> 168317.39 | G68: =F68*E68 -> 77426 | K68: 49904 | O68: =L68+M68+N68 -> 0 | P68: =K68+L68+M68+N68 -> 49904 | Q68: =P68*$Q$12 -> 707 | R68: =P68*$R$12 -> 854 | S68: =P68+Q68+R68 -> 51465 | T68: =S68*'НМЦК подряд'!$C$16*'НМЦК подряд'!$E$16 -> 77426 | U68: =L68+M68+N68 -> 0
A69: 02.01.24 | B69: ЛСР №02-01-01, п. 54, 55, 57,58, 59, 60, ЛСР 09-02-01 п. 1 | C69: Омоноличивание верхнего строения пирса | D69: м3 | E69: 90 | F69: =T69/E69 -> 84624.03 | G69: =F69*E69 -> 7616162.7 | K69: =2489260+1121324+39690+74444+84526+902074 -> 4711318 | M69: =9.47*$N$11+3273 -> 41652 | N69: =E69*0.4275*N11 -> 155926 | O69: =L69+M69+N69 -> 197578 | P69: =K69+L69+M69+N69 -> 4908896 | Q69: =P69*$Q$12 -> 69522 | R69: =P69*$R$12 -> 84030 | S69: =P69+Q69+R69 -> 5062448 | T69: =S69*'НМЦК подряд'!$C$16*'НМЦК подряд'!$E$16 -> 7616163 | U69: =L69+M69+N69 -> 197578
A70: 02.01.25 | B70: ЛСР №02-01-01, п. 65-68 | C70: Устройство колесоотбойников пирса | D70: м3 | E70: 8,1 | F70: =T70/E70 -> 64300.49 | G70: =F70*E70 -> 520833.97 | K70: =133924+78315+4158+100971 -> 317368 | M70: =(0.8+0.25+0.01)*N11 -> 4296 | N70: =E70*0.4275*N11 -> 14033 | O70: =L70+M70+N70 -> 18329 | P70: =K70+L70+M70+N70 -> 335697 | Q70: =P70*$Q$12 -> 4754 | R70: =P70*$R$12 -> 5746 | S70: =P70+Q70+R70 -> 346197 | T70: =S70*'НМЦК подряд'!$C$16*'НМЦК подряд'!$E$16 -> 520834 | U70: =L70+M70+N70 -> 18329
C71: Возведение верхнего строения причала | O71: =L71+M71+N71 -> 0 | P71: =K71+L71+M71+N71 -> 0 | Q71: =P71*$Q$12 -> 0 | R71: =P71*$R$12 -> 0 | S71: =P71+Q71+R71 -> 0 | T71: =S71*'НМЦК подряд'!$C$16*'НМЦК подряд'!$E$16 -> 0 | U71: =L71+M71+N71 -> 0
A72: 02.01.26 | B72: ЛСР №02-01-01, п. 14, 15 17-18, ЛСР 09-02-01 п. 1 | C72: Омоноличивание верхнего строения причала | D72: м3 | E72: 237 | F72: =T72/E72 -> 86022.19 | G72: =F72*E72 -> 20387259 | K72: =6555058+3446791+122024+2499517 -> 12623390 | M72: =26.24*N11 -> 106342 | N72: =E72*0.4275*N11 -> 410604 | O72: =L72+M72+N72 -> 516946 | P72: =K72+L72+M72+N72 -> 13140336 | Q72: =P72*$Q$12 -> 186099 | R72: =P72*$R$12 -> 224936 | S72: =P72+Q72+R72 -> 13551371 | T72: =S72*'НМЦК подряд'!$C$16*'НМЦК подряд'!$E$16 -> 20387260 | U72: =L72+M72+N72 -> 516946
A73: 02.01.27 | B73: ЛСР №02-01-01, п. 40 | C73: Устройство антисейсмических швов | D73: м | E73: 29.2 | F73: =T73/E73 -> 3214.86 | G73: =F73*E73 -> 93873.91 | K73: 60505 | O73: =L73+M73+N73 -> 0 | P73: =K73+L73+M73+N73 -> 60505 | Q73: =P73*$Q$12 -> 857 | R73: =P73*$R$12 -> 1036 | S73: =P73+Q73+R73 -> 62398 | T73: =S73*'НМЦК подряд'!$C$16*'НМЦК подряд'!$E$16 -> 93874 | U73: =L73+M73+N73 -> 0
A74: 02.01.28 | B74: ЛСР №02-01-01, п. 19-22, ЛСР 09-02-01 п. 1 | C74: Устройство колесоотбойников | D74: м3 | E74: 4,2 | F74: =T74/E74 -> 63307.62 | G74: =F74*E74 -> 265892 | K74: =69411+51895+40608+2156+30 -> 164100 | N74: =E74*0.4275*N11 -> 7277 | O74: =L74+M74+N74 -> 7277 | P74: =K74+L74+M74+N74 -> 171377 | Q74: =P74*$Q$12 -> 2427 | R74: =P74*$R$12 -> 2934 | S74: =P74+Q74+R74 -> 176738 | T74: =S74*'НМЦК подряд'!$C$16*'НМЦК подряд'!$E$16 -> 265892 | U74: =L74+M74+N74 -> 7277
C75: Поддерживающий каркас | O75: =L75+M75+N75 -> 0 | P75: =K75+L75+M75+N75 -> 0 | Q75: =P75*$Q$12 -> 0 | R75: =P75*$R$12 -> 0 | S75: =P75+Q75+R75 -> 0 | T75: =S75*'НМЦК подряд'!$C$16*'НМЦК подряд'!$E$16 -> 0 | U75: =L75+M75+N75 -> 0
A76: 02.01.29 | B76: ЛСР №02-01-01, п. 16, ЛСР 09-02-01 п. 1 | C76: Монтаж каркаса поддерживающего КП-1 из арматуры | D76: т | E76: 0,46 | F76: =T76/E76 -> 174604.35 | G76: =F76*E76 -> 80318 | K76: 49904 | M76: =E76*N11 -> 1864 | O76: =L76+M76+N76 -> 1864 | P76: =K76+L76+M76+N76 -> 51768 | Q76: =P76*$Q$12 -> 733 | R76: =P76*$R$12 -> 886 | S76: =P76+Q76+R76 -> 53387 | T76: =S76*'НМЦК подряд'!$C$16*'НМЦК подряд'!$E$16 -> 80318 | U76: =L76+M76+N76 -> 1864
A77: 02.01.30 | B77: ЛСР №02-01-01, п. 34-37, ЛСР 09-02-01 п. 1 | C77: Устройство монолитного железобетонного массива | D77: м3 | E77: 55 | F77: =T77/E77 -> 46224.44 | G77: =F77*E77 -> 2542344.2 | K77: =259418+633876+594635+21051 -> 1508980 | M77: =(5.6+0.73+0.25+1.9)*N11 -> 34366 | N77: =E77*0.4275*N11 -> 95288 | O77: =L77+M77+N77 -> 129654 | P77: =K77+L77+M77+N77 -> 1638634 | Q77: =P77*$Q$12 -> 23207 | R77: =P77*$R$12 -> 28050 | S77: =P77+Q77+R77 -> 1689891 | T77: =S77*'НМЦК подряд'!$C$16*'НМЦК подряд'!$E$16 -> 2542344 | U77: =L77+M77+N77 -> 129654
A78: 02.01.31 | B78: ЛСР №02-01-01, п. 32-33 | C78: Устройство бетонной подготовки | D78: м3 | E78: 11 | F78: =T78/E78 -> 15126.64 | G78: =F78*E78 -> 166393.04 | K78: =27762+79484 -> 107246 | O78: =L78+M78+N78 -> 0 | P78: =K78+L78+M78+N78 -> 107246 | Q78: =P78*$Q$12 -> 1519 | R78: =P78*$R$12 -> 1836 | S78: =P78+Q78+R78 -> 110601 | T78: =S78*'НМЦК подряд'!$C$16*'НМЦК подряд'!$E$16 -> 166393 | U78: =L78+M78+N78 -> 0
A79: 02.01.32 | B79: ЛСР №02-01-01, п. 37-39 | C79: Укрепление подпричального откоса камнем | D79: м3 | E79: =352+470 -> 822 | F79: =T79/E79 -> 8878.68 | G79: =F79*E79 -> 7298275 | K79: =3002469+744841+956698 -> 4704008 | O79: =L79+M79+N79 -> 0 | P79: =K79+L79+M79+N79 -> 4704008 | Q79: =P79*$Q$12 -> 66620 | R79: =P79*$R$12 -> 80523 | S79: =P79+Q79+R79 -> 4851151 | T79: =S79*'НМЦК подряд'!$C$16*'НМЦК подряд'!$E$16 -> 7298278 | U79: =L79+M79+N79 -> 0
A80: 02.01.33 | B80: ЛСР №02-01-01, п. 73-74 | C80: Обваловка свай пирса камнем | D80: м3 | E80: 328 | F80: =T80/E80 -> 9884.15 | G80: =F80*E80 -> 3242001.2 | K80: =1198066+891522 -> 2089588 | O80: =L80+M80+N80 -> 0 | P80: =K80+L80+M80+N80 -> 2089588 | Q80: =P80*$Q$12 -> 29594 | R80: =P80*$R$12 -> 35770 | S80: =P80+Q80+R80 -> 2154952 | T80: =S80*'НМЦК подряд'!$C$16*'НМЦК подряд'!$E$16 -> 3242002 | U80: =L80+M80+N80 -> 0
C81: Элементы обустройства | O81: =L81+M81+N81 -> 0 | P81: =K81+L81+M81+N81 -> 0 | Q81: =P81*$Q$12 -> 0 | R81: =P81*$R$12 -> 0 | S81: =P81+Q81+R81 -> 0 | T81: =S81*'НМЦК подряд'!$C$16*'НМЦК подряд'!$E$16 -> 0 | U81: =L81+M81+N81 -> 0
A82: 02.01.34 | B82: ЛСР №02-01-01, п. 41-42 | C82: Монтаж шлагбаума | D82: шт | E82: 6 | F82: =T82/E82 -> 35295.67 | G82: =F82*E82 -> 211774.02 | K82: =86464+50032 -> 136496 | O82: =L82+M82+N82 -> 0 | P82: =K82+L82+M82+N82 -> 136496 | Q82: =P82*$Q$12 -> 1933 | R82: =P82*$R$12 -> 2337 | S82: =P82+Q82+R82 -> 140766 | T82: =S82*'НМЦК подряд'!$C$16*'НМЦК подряд'!$E$16 -> 211774 | U82: =L82+M82+N82 -> 0
A83: 02.01.35 | B83: ЛСР №02-01-01, п. 27, 23-24, ЛСР 09-02-01 п. 1 | C83: Установка стального перильного ограждения | D83: м | E83: 75.6 | F83: =T83/E83 -> 5131.24 | G83: =F83*E83 -> 387921.74 | K83: =225900+8446+9591 -> 243937 | M83: =(1.4969+0.0066)*N11 -> 6093 | O83: =L83+M83+N83 -> 6093 | P83: =K83+L83+M83+N83 -> 250030 | Q83: =P83*$Q$12 -> 3541 | R83: =P83*$R$12 -> 4280 | S83: =P83+Q83+R83 -> 257851 | T83: =S83*'НМЦК подряд'!$C$16*'НМЦК подряд'!$E$16 -> 387922 | U83: =L83+M83+N83 -> 6093
A84: 02.01.36 | B84: ЛСР №02-01-01, п. 25, ЛСР 09-02-01 п. 1 | C84: Навеска отбойных устройств | D84: тн | E84: 4.6 | F84: =T84/E84 -> 274517.17 | G84: =F84*E84 -> 1262779 | K84: 742954 | M84: =0.906*N12+24730+9060 -> 70954 | O84: =L84+M84+N84 -> 70954 | P84: =K84+L84+M84+N84 -> 813908 | Q84: =P84*$Q$12 -> 11527 | R84: =P84*$R$12 -> 13932 | S84: =P84+Q84+R84 -> 839367 | T84: =S84*'НМЦК подряд'!$C$16*'НМЦК подряд'!$E$16 -> 1262779 | U84: =L84+M84+N84 -> 70954
A85: 02.01.37 | B85: ЛСР №02-01-01, п. 26 | C85: Монтаж стальных скоб-трапов | D85: тн | E85: 0.072 | F85: =T85/E85 -> 315597.22 | G85: =F85*E85 -> 22723 | K85: 14646 | O85: =L85+M85+N85 -> 0 | P85: =K85+L85+M85+N85 -> 14646 | Q85: =P85*$Q$12 -> 207 | R85: =P85*$R$12 -> 251 | S85: =P85+Q85+R85 -> 15104 | T85: =S85*'НМЦК подряд'!$C$16*'НМЦК подряд'!$E$16 -> 22723 | U85: =L85+M85+N85 -> 0
A86: 02.01.38 | B86: ЛСР №02-01-01, п. 28-30, 69, 70 | C86: Установка швартовых тумб | D86: шт | E86: 4 | F86: =T86/E86 -> 397589.5 | G86: =F86*E86 -> 1590358 | K86: =273409+234498+4620+273409+234498+4620-10 -> 1025044 | O86: =L86+M86+N86 -> 0 | P86: =K86+L86+M86+N86 -> 1025044 | Q86: =P86*$Q$12 -> 14517 | R86: =P86*$R$12 -> 17547 | S86: =P86+Q86+R86 -> 1057108 | T86: =S86*'НМЦК подряд'!$C$16*'НМЦК подряд'!$E$16 -> 1590358 | U86: =L86+M86+N86 -> 0
A87: 02.01.39 | B87: ЛСР №02-01-01, п. 75-76 | C87: Установка светодиодных сигнальных огоней для причалов | D87: шт. | E87: 5 | F87: =T87/E87 -> 7429.8 | G87: =F87*E87 -> 37149 | K87: =9281+14663 -> 23944 | O87: =L87+M87+N87 -> 0 | P87: =K87+L87+M87+N87 -> 23944 | Q87: =P87*$Q$12 -> 339 | R87: =P87*$R$12 -> 410 | S87: =P87+Q87+R87 -> 24693 | T87: =S87*'НМЦК подряд'!$C$16*'НМЦК подряд'!$E$16 -> 37149 | U87: =L87+M87+N87 -> 0
C88: Итого: раздел 2.1. | G88: =SUM(G49:G87) -> 1.2473053e+08 | K88: =SUM(K49:K87) -> 78038311 | O88: =SUM(O49:O87) -> 2355089 | P88: =SUM(P49:P87) -> 80393400 | Q88: =SUM(Q49:Q87) -> 1138565 | R88: =SUM(R49:R87) -> 1376172 | S88: =SUM(S49:S87) -> 82908137 | T88: =SUM(T49:T87) -> 124730537 | U88: =SUM(U49:U87) -> 2355089
A89: Раздел 2.2. Дноуглубительные работы | K89: =78038311-K88 -> 0 | O89: =L89+M89+N89 -> 0 | P89: =K89+L89+M89+N89 -> 0 | Q89: =P89*$Q$12 -> 0 | R89: =P89*$R$12 -> 0 | S89: =K89+Q89+R89 -> 0 | T89: =S89*'НМЦК подряд'!$C$16*'НМЦК подряд'!$E$16 -> 0 | U89: =L89+M89+N89 -> 0
A90: 02.02.1 | B90: ЛСР №02-01-02, п. 1 | C90: Дноуглубительные работы | D90: м3 | E90: 1249 | F90: =T90/E90 -> 2893.68 | G90: =F90*E90 -> 3614206.3 | K90: 2329487 | O90: =L90+M90+N90 -> 0 | P90: =K90+L90+M90+N90 -> 2329487 | Q90: =P90*$Q$12 -> 32991 | R90: =P90*$R$12 -> 39876 | S90: =P90+Q90+R90 -> 2402354 | T90: =S90*'НМЦК подряд'!$C$16*'НМЦК подряд'!$E$16 -> 3614204 | U90: =L90+M90+N90 -> 0
C91: Итого: раздел 2.2. | G91: =SUM(G90) -> 3614206.3 | H91: =SUM(H90) -> 0 | I91: =SUM(I90) -> 0 | J91: =SUM(J90) -> 0 | K91: =SUM(K90) -> 2329487 | O91: =SUM(O90) -> 0 | P91: =SUM(P90) -> 2329487 | Q91: =SUM(Q90) -> 32991 | R91: =SUM(R90) -> 39876 | S91: =SUM(S90) -> 2402354 | T91: =SUM(T90) -> 3614204 | U91: =SUM(U90) -> 0
A92: Раздел 2.3. Перенос автобусного павильона для пассажиров. Правый берег | O92: =L92+M92+N92 -> 0 | P92: =K92+L92+M92+N92 -> 0 | Q92: =P92*$Q$12 -> 0 | R92: =P92*$R$12 -> 0 | S92: =K92+Q92+R92 -> 0 | T92: =S92*'НМЦК подряд'!$C$16*'НМЦК подряд'!$E$16 -> 0 | U92: =L92+M92+N92 -> 0
A93: 02.03.1 | B93: ЛСР №02-01-03, п. 1-6 | C93: Демонтаж существующего автопавильона с погрузкой и транспортировкой на временную площадку складирования | D93: шт | E93: 1 | F93: =T93/E93 -> 194234 | G93: =F93*E93 -> 194234 | J93: =118+1234+139+381+1179+49 -> 3100 | K93: =6486+49534+5498+14940+47124+1609 -> 125191 | O93: =L93+M93+N93 -> 0 | P93: =K93+L93+M93+N93 -> 125191 | Q93: =P93*$Q$12 -> 1773 | R93: =P93*$R$12 -> 2143 | S93: =P93+Q93+R93 -> 129107 | T93: =S93*'НМЦК подряд'!$C$16*'НМЦК подряд'!$E$16 -> 194234 | U93: =L93+M93+N93 -> 0
A94: 02.03.2 | B94: ЛСР №02-01-03, п. 7-8 | C94: Погрузка и доставка элементов существующего автопавильона от временной площадки складирования до места работ | D94: шт | E94: 1 | F94: =T94/E94 -> 1795 | G94: =F94*E94 -> 1795 | J94: 67 | K94: =276+881 -> 1157 | O94: =L94+M94+N94 -> 0 | P94: =K94+L94+M94+N94 -> 1157 | Q94: =P94*$Q$12 -> 16 | R94: =P94*$R$12 -> 20 | S94: =P94+Q94+R94 -> 1193 | T94: =S94*'НМЦК подряд'!$C$16*'НМЦК подряд'!$E$16 -> 1795 | U94: =L94+M94+N94 -> 0
A95: 02.03.3 | B95: ЛСР №02-01-03, п. 9-29, ЛСР 09-02-01 п. 1 | C95: Монтаж железобетонного автобусного павильона с установкой скамьи, урны | D95: шт | E95: 1 | F95: =T95/E95 -> 557974 | G95: =F95*E95 -> 557974 | J95: 9323 | K95: =414048-K94-K93 -> 287700 | L95: =17.75*N11 -> 71935 | O95: =L95+M95+N95 -> 71935 | P95: =K95+L95+M95+N95 -> 359635 | Q95: =P95*$Q$12 -> 5093 | R95: =P95*$R$12 -> 6156 | S95: =P95+Q95+R95 -> 370884 | T95: =S95*'НМЦК подряд'!$C$16*'НМЦК подряд'!$E$16 -> 557974 | U95: =L95+M95+N95 -> 71935
C96: Итого: раздел 2.3. | G96: =SUM(G93:G95) -> 754003 | K96: =SUM(K93:K95) -> 414048 | O96: =SUM(O93:O95) -> 71935 | P96: =SUM(P93:P95) -> 485983 | Q96: =SUM(Q93:Q95) -> 6882 | R96: =SUM(R93:R95) -> 8319 | S96: =SUM(S93:S95) -> 501184 | T96: =SUM(T93:T95) -> 754003 | U96: =SUM(U93:U95) -> 71935
A97: Раздел 2.4. Подъездная дорога. Правый берег | O97: =L97+M97+N97 -> 0 | P97: =K97+L97+M97+N97 -> 0 | Q97: =P97*$Q$12 -> 0 | R97: =P97*$R$12 -> 0 | S97: =K97+Q97+R97 -> 0 | T97: =S97*'НМЦК подряд'!$C$16*'НМЦК подряд'!$E$16 -> 0 | U97: =L97+M97+N97 -> 0
A98: Раздел 2.4.1 Восстановление покрытия | O98: =L98+M98+N98 -> 0 | P98: =K98+L98+M98+N98 -> 0 | Q98: =P98*$Q$12 -> 0 | R98: =P98*$R$12 -> 0 | S98: =K98+Q98+R98 -> 0 | T98: =S98*'НМЦК подряд'!$C$16*'НМЦК подряд'!$E$16 -> 0 | U98: =L98+M98+N98 -> 0
C99: Замена пучинистого основания | O99: =L99+M99+N99 -> 0 | P99: =K99+L99+M99+N99 -> 0 | Q99: =P99*$Q$12 -> 0 | R99: =P99*$R$12 -> 0 | S99: =K99+Q99+R99 -> 0 | T99: =S99*'НМЦК подряд'!$C$16*'НМЦК подряд'!$E$16 -> 0 | U99: =L99+M99+N99 -> 0
A100: 02.04.1 | B100: ЛСР №02-01-04, п. 1 | C100: Фрезеровка существующего асфальтобетона с погрузкой в автосамосвалы и транспортировкой до 9 км | D100: м2 | E100: 130 | F100: =T100/E100 -> 426.41 | G100: =F100*E100 -> 55433.3 | K100: =31264+121204/670.7*13*1.9 -> 35728 | O100: =L100+M100+N100 -> 0 | P100: =K100+L100+M100+N100 -> 35728 | Q100: =P100*$Q$12 -> 506 | R100: =P100*$R$12 -> 612 | S100: =P100+Q100+R100 -> 36846 | T100: =S100*'НМЦК подряд'!$C$16*'НМЦК подряд'!$E$16 -> 55433 | U100: =L100+M100+N100 -> 0
A101: 02.04.2 | B101: ЛСР №02-01-04, п. 2, 4 | C101: Разработка грунта 1 группы, y=1,70 т/м3, экскаватором с емкостью ковша 1,0 м3 с последующей погрузкой в автосамосвалы и транспортировкой до 9 км | D101: м3 | E101: 505 | F101: =T101/E101 -> 449.55 | G101: =F101*E101 -> 227022.75 | K101: =29585+121204/670.7*380*1.7 -> 146325 | O101: =L101+M101+N101 -> 0 | P101: =K101+L101+M101+N101 -> 146325 | Q101: =P101*$Q$12 -> 2072 | R101: =P101*$R$12 -> 2505 | S101: =P101+Q101+R101 -> 150902 | T101: =S101*'НМЦК подряд'!$C$16*'НМЦК подряд'!$E$16 -> 227023 | U101: =L101+M101+N101 -> 0
A102: 02.04.3 | B102: ЛСР №02-01-04, п. 3 | C102: Разработка крупнообломочного грунта 4 группы y=2,26 т/м3 экскаватором емкостью ковша 1,0 м3 с погрузкой и транспортировкой на расстояние до 43 км в основание дорожной одежды из карьера (км 381 а/д Мильково-Ключи-Усть-Камчатск) | D102: м3 | E102: 505 | F102: =T102/E102 -> 186.28 | G102: =F102*E102 -> 94071.4 | H102: не учтена транспортировка | K102: 60632 | O102: =L102+M102+N102 -> 0 | P102: =K102+L102+M102+N102 -> 60632 | Q102: =P102*$Q$12 -> 859 | R102: =P102*$R$12 -> 1038 | S102: =P102+Q102+R102 -> 62529 | T102: =S102*'НМЦК подряд'!$C$16*'НМЦК подряд'!$E$16 -> 94071 | U102: =L102+M102+N102 -> 0
...

Sheet Проект сметы 
E1: "Утверждаю"
F2: Начальник КГКУ "Камчатуправтодор"
F3: ______________________Щегловский В.С.
A5: Проект Сметы контракта
A7: =Справка!B5 -> Строительство причальных сооружений через протоку Озерная в Усть-Камчатском районе Камчатского края
A9: № п/п | B9: Наименование конструктивных решений (элементов), комплексов (видов) работ | C9: Ед. идм. | D9: Кол-во | E9: Единичная расценка, руб | F9: Общая стоимость, руб
A11: 1 | B11: 3 | C11: 4 | D11: 5 | E11: 6 | F11: 7
A12: Глава 1. Подготовка территории строительства
A13: Раздел 1.1. Восстановление оси трассы
A14: 01.01.1 | B14: Восстановление оси трассы (правый берег) | C14: км | D14: 0.335 | E14: 36217.91 | F14: =E14*D14 -> 12133
A15: 01.01.2 | B15: Восстановление оси трассы (левый берег) | C15: км | D15: 0.9 | E15: 3326.67 | F15: =E15*D15 -> 2994
B16: Итого: раздел 1.1. | F16: =SUM(F14:F15) -> 15127
A17: Раздел 1.2. Демонтаж конструкций причального сооружения. Правый берег
A18: 01.02.1 | B18: Демонтаж существующего деревянного причала (правый берег) с погрузкой и транспортировкой на расстояние до 9 км | C18: комплекс | D18: 1 | E18: 5650864 | F18: =E18*D18 -> 5650864
A19: 01.02.2 | B19: Демонтаж существующего пирса (правый берег) с погрузкой и транспортировкой на расстояние до 9 км | C19: комплекс | D19: 1 | E19: 6285005 | F19: =E19*D19 -> 6285005
B20: Итого: раздел 1.2. | F20: =SUM(F18:F19) -> 11935869
A21: Раздел 1.3. Демонтаж конструкций причала левого берега.
A22: Раздел 1.3.1 Временный пирс (судно-лихтер)
A23: 01.03.1 | B23: Срезка надстроек, возвышающихся над уровнем воды | C23: м | D23: 750 | E23: 871.52 | F23: =D23*E23 -> 653640
A24: 01.03.2 | B24: Откачка воды из корпуса судна-лихтера передвижным насосом | C24: м3 | D24: 100 | E24: 140.15 | F24: =D24*E24 -> 14015
A25: 01.03.3 | B25: Очистка трюма судна-лихтера от грунта | C25: м3 | D25: 100 | E25: 228.57 | F25: =D25*E25 -> 22857
A26: 01.03.4 | B26: Выравнивание берега до пляжного откоса | C26: м3 | D26: 200 | E26: 39.77 | F26: =D26*E26 -> 7954
A27: 01.03.5 | B27: Забивка свай фундамента анкерной опоры | C27: т | D27: 6.57 | E27: 171729.98 | F27: =D27*E27 -> 1128266
A28: 01.03.6 | B28: Монтаж анкерной опоры в виде ростверка | C28: м3 | D28: 12 | E28: 28581.75 | F28: =D28*E28 -> 342981
A29: 01.03.7 | B29: Откачка воды из трюма лихтера | C29: м3 | D29: 200 | E29: 140.13 | F29: =D29*E29 -> 28026
A30: 01.03.8 | B30: Вытаскивание корпуса судна-лихтера на берег | C30: т | D30: 100 | E30: 8086.47 | F30: =D30*E30 -> 808647
A31: 01.03.9 | B31: Демонтаж анкерных опор в виде ростверка | C31: м3 | D31: 12 | E31: 146671.75 | F31: =D31*E31 -> 1760061
A32: 01.03.10 | B32: Демонтаж свай | C32: т | D32: 6.57 | E32: 27220.55 | F32: =D32*E32 -> 178839.01
A33: 01.03.11 | B33: Перевозка автосамосвалами металлолома на расстояние до 10 км | C33: т | D33: 150 | E33: 280.38 | F33: =D33*E33 -> 42057
B34: Итого по Разделу 1.3.1 | F34: =SUM(F23:F33) -> 4987343
A35: Раздел 1.3.2 Временный причал (плашкоут)
A36: 01.03.12 | B36: Очистка корпуса плашкоута от грунта экскаватором | C36: м3 | D36: 200 | E36: 157.66 | F36: =D36*E36 -> 31532
A37: 01.03.13 | B37: Откачка воды из корпуса плашкоута насосами | C37: т | D37: 100 | E37: 140.15 | F37: =D37*E37 -> 14015
A38: 01.03.14 | B38: Вытаскивание корпуса плашкоута на берег | C38: т | D38: 50 | E38: 14942.1 | F38: =D38*E38 -> 747105
A39: 01.03.15 | B39: Перевозка автосамосвалами металлолома на расстояние до 10 км | C39: т | D39: 87 | E39: 280.38 | F39: =D39*E39 -> 24393.06
B40: Итого по Разделу 1.3.2 | F40: =SUM(F36:F39) -> 817045.06
B41: Итого по Разделу 1.3. | F41: =F40+F34 -> 5804388
A42: Раздел 1.4. Демонтаж существущего обустройства
A43: 01.04.1 | B43: Демонтаж дорожных знаков на металлических стойках с транспортировкой на полигон ТБО на расстояние до 9 км | C43: шт | D43: 4 | E43: 7771.5 | F43: =E43*D43 -> 31086
B44: Итого: раздел 1.4. | F44: =F43 -> 31086
B45: Итого: Глава 1. | F45: =F44+F41+F20+F16 -> 17786470
A46: Глава 2. Причальное сооружение (правый берег)
A47: Раздел 2.1. Конструктивные элементы (правый берег)
B48: Причал
A49: 02.01.1 | B49: Погружение вертикальных свай С-1 | C49: тн | D49: 23.81 | E49: 64335.95 | F49: =E49*D49 -> 1531839
A50: 02.01.2 | B50: Погружение вертикальных свай С-2 | C50: тн | D50: 76.73 | E50: 64335.96 | F50: =E50*D50 -> 4936498.2
A51: 02.01.3 | B51: Погружение наклонных свай С-3 | C51: тн | D51: 76.73 | E51: 77839.31 | F51: =E51*D51 -> 5972610.3
A52: 02.01.4 | B52: Сваи из стальных труб d=630 мм, толщина стенки 12 мм | C52: тн | D52: 179 | E52: 154224.96 | F52: =E52*D52 -> 27606268
A53: 02.01.5 | B53: Установка арматурного каркаса | C53: шт | D53: 67 | E53: 30016.82 | F53: =E53*D53 -> 2011126.9
A54: 02.01.6 | B54: Арматурные каркасы | C54: тн | D54: 19.27 | E54: 173941.62 | F54: =E54*D54 -> 3351855
A55: 02.01.7 | B55: Заполнение свай бетоном | C55: м3 | D55: 155.44 | E55: 45412.91 | F55: =E55*D55 -> 7058982.7
A56: 02.01.8 | B56: Погружение шпунтов | C56: тн | D56: 59.7 | E56: 236099.7 | F56: =E56*D56 -> 14095152
A57: 02.01.9 | B57: Нанесение вручную праймера на стальную надвобную поверхность сваи (шпунта) | C57: м2 | D57: =201+165 -> 366 | E57: 668.95 | F57: =E57*D57 -> 244835.7
A58: 02.01.10 | B58: Нанесение обматыванием по спирали ленты на надводную поверхность стальной сваи | C58: м2 | D58: =126+113 -> 239 | E58: 20854.92 | F58: =E58*D58 -> 4984325.9
A59: 02.01.11 | B59: Монтаж кожуха на надводную поверхность стальной сваи | C59: м2 | D59: =126+113 -> 239 | E59: 6436.7 | F59: =E59*D59 -> 1538371.3
A60: 02.01.12 | B60: Нанесение мастики на подготовленную стальную поверхность над водой | C60: м2 | D60: 108.2 | E60: 1524.43 | F60: =E60*D60 -> 164943.33
A61: 02.01.13 | B61: Устройство наголовника свай НС-1, НС-2, НС-3 | C61: тн | D61: =1.67+0.9+0.24 -> 2.81 | E61: 321893.59 | F61: =E61*D61 -> 904520.99
A62: 02.01.14 | B62: Устройство связи СВ-1, СВ-2, СВ-3 на причале (стальная конструкция) | C62: тн | D62: 4.6328 | E62: 289602.83 | F62: =E62*D62 -> 1341672
B63: Возведение верхнего строения пирса
A64: 02.01.15 | B64: Устройство связи СВ-1, СВ-4, СВ-5 на пирсе (стальная конструкция) | C64: тн | D64: 6.0149 | E64: 289969.74 | F64: =E64*D64 -> 1744139
A65: 02.01.16 | B65: Омоноличивание оголовока пирса | C65: м3 | D65: 16 | E65: 50045.13 | F65: =E65*D65 -> 800722.08
A66: 02.01.17 | B66: Устройство антисейсмических швов | C66: м | D66: 5.2 | E66: 3214.23 | F66: =E66*D66 -> 16714
A67: 02.01.18 | B67: Армирование оголовка пирса | C67: т | D67: =2.5+1.4+0.14 -> 4.04 | E67: 154077.72 | F67: =E67*D67 -> 622473.99
A68: 02.01.19 | B68: Монтаж каркаса поддерживающего КП-1 из арматуры | C68: т | D68: 0,46 | E68: 168317.39 | F68: =E68*D68 -> 77426
A69: 02.01.20 | B69: Омоноличивание верхнего строения пирса | C69: м3 | D69: 90 | E69: 84624.03 | F69: =E69*D69 -> 7616162.7
A70: 02.01.21 | B70: Устройство колесоотбойников пирса | C70: м3 | D70: 8,1 | E70: 64300.49 | F70: =E70*D70 -> 520833.97
B71: Возведение верхнего строения причала
A72: 02.01.22 | B72: Омоноличивание верхнего строения причала | C72: м3 | D72: 237 | E72: 86022.19 | F72: =E72*D72 -> 20387259
A73: 02.01.23 | B73: Устройство антисейсмических швов | C73: м | D73: 29.2 | E73: 3214.86 | F73: =E73*D73 -> 93873.91
A74: 02.01.24 | B74: Устройство колесоотбойников | C74: м3 | D74: 4,2 | E74: 63307.62 | F74: =E74*D74 -> 265892
B75: Поддерживающий каркас
A76: 02.01.25 | B76: Монтаж каркаса поддерживающего КП-1 из арматуры | C76: т | D76: 0,46 | E76: 174604.35 | F76: =E76*D76 -> 80318
A77: 02.01.26 | B77: Устройство монолитного железобетонного массива | C77: м3 | D77: 55 | E77: 46224.44 | F77: =E77*D77 -> 2542344.2
A78: 02.01.27 | B78: Устройство бетонной подготовки | C78: м3 | D78: 11 | E78: 15126.64 | F78: =E78*D78 -> 166393.04
A79: 02.01.28 | B79: Укрепление подпричального откоса камнем | C79: м3 | D79: =352+470 -> 822 | E79: 8878.68 | F79: =E79*D79 -> 7298275
A80: 02.01.29 | B80: Обваловка свай пирса камнем | C80: м3 | D80: 328 | E80: 9884.15 | F80: =E80*D80 -> 3242001.2
B81: Элементы обустройства
A82: 02.01.30 | B82: Монтаж шлагбаума | C82: шт | D82: 6 | E82: 35295.67 | F82: =E82*D82 -> 211774.02
A83: 02.01.31 | B83: Установка стального перильного ограждения | C83: м | D83: 75.6 | E83: 5131.24 | F83: =E83*D83 -> 387921.74
A84: 02.01.32 | B84: Навеска отбойных устройств | C84: тн | D84: 4.6 | E84: 274517.17 | F84: =E84*D84 -> 1262779
A85: 02.01.33 | B85: Монтаж стальных скоб-трапов | C85: тн | D85: 0.072 | E85: 315597.22 | F85: =E85*D85 -> 22723
A86: 02.01.34 | B86: Установка швартовых тумб | C86: шт | D86: 4 | E86: 397589.5 | F86: =E86*D86 -> 1590358
A87: 02.01.35 | B87: Установка светодиодных сигнальных огоней для причалов | C87: шт. | D87: 5 | E87: 7429.8 | F87: =E87*D87 -> 37149
B88: Итого: раздел 2.1. | F88: =SUM(F49:F87) -> 1.2473053e+08
A89: Раздел 2.2. Дноуглубительные работы
A90: 02.02.1 | B90: Дноуглубительные работы | C90: м3 | D90: 1249 | E90: 2893.68 | F90: =E90*D90 -> 3614206.3
B91: Итого: раздел 2.2. | F91: =SUM(F90) -> 3614206.3
A92: Раздел 2.3. Перенос автобусного павильона для пассажиров. Правый берег
A93: 02.03.1 | B93: Демонтаж существующего автопавильона с погрузкой и транспортировкой на временную площадку складирования | C93: шт | D93: 1 | E93: 194234 | F93: =E93*D93 -> 194234
A94: 02.03.2 | B94: Погрузка и доставка элементов существующего автопавильона от временной площадки складирования до места работ | C94: шт | D94: 1 | E94: 1795 | F94: =E94*D94 -> 1795
A95: 02.03.3 | B95: Монтаж железобетонного автобусного павильона с установкой скамьи, урны | C95: шт | D95: 1 | E95: 557974 | F95: =E95*D95 -> 557974
B96: Итого: раздел 2.3. | F96: =SUM(F93:F95) -> 754003
A97: Раздел 2.4. Подъездная дорога. Правый берег
A98: Раздел 2.4.1 Восстановление покрытия
B99: Замена пучинистого основания
A100: 02.04.1 | B100: Фрезеровка существующего асфальтобетона с погрузкой в автосамосвалы и транспортировкой до 9 км | C100: м2 | D100: 130 | E100: 426.41 | F100: =E100*D100 -> 55433.3
A101: 02.04.2 | B101: Разработка грунта 1 группы, y=1,70 т/м3, экскаватором с емкостью ковша 1,0 м3 с последующей погрузкой в автосамосвалы и транспортировкой до 9 км | C101: м3 | D101: 505 | E101: 449.55 | F101: =E101*D101 -> 227022.75
A102: 02.04.3 | B102: Разработка крупнообломочного грунта 4 группы y=2,26 т/м3 экскаватором емкостью ковша 1,0 м3 с погрузкой и транспортировкой на расстояние до 43 км в основание дорожной одежды из карьера (км 381 а/д Мильково-Ключи-Усть-Камчатск) | C102: м3 | D102: 505 | E102: 186.28 | F102: =E102*D102 -> 94071.4
A103: 02.04.4 | B103: Уплотнение грунта | C103: м3 | D103: 505 | E103: 70.57 | F103: =E103*D103 -> 35637.85
B104: Устройство новой дорожной на сопряжении с причальным сооружением
...

Sheet Ведомость объемов
D1: УТВЕРЖДАЮ
C2: Начальник КГКУ "Камчатуправтодор"
C3: ______________В.С. Щегловский
C4: «___»______________2026 г.
A6: Ведомость объемов конструктивных решений (элементов) и комплексов (видов) работ, оборудования
A7: Строительство причальных сооружений через протоку Озерная в Усть-Камчатском районе Камчатского края
A8: (наименование объекта)
A9: № п/п | B9: Номера сметных расчетов (смет) и подиций в сметных расчетах (сметах), относящиеся к соответсвующим конструктивным решениям (элементам), комплексам (видам) работ | C9: Наименование конструктивных решений (элементов), комплексов (видов) работ | D9: Ед. идм. | E9: Кол-во
A11: 1 | B11: 2 | C11: 3 | D11: 4 | E11: 5
A12: Глава 1. Подготовка территории строительства
A13: Раздел 1.1. Восстановление оси трассы
A14: 01.01.1 | B14: Расчет №1 | C14: Восстановление оси трассы (правый берег) | D14: км | E14: 0.335
A15: 01.01.2 | B15: Расчет №2 | C15: Восстановление оси трассы (левый берег) | D15: км | E15: 0.9
A16: Раздел 1.2. Демонтаж конструкций причального сооружения. Правый берег
A17: 01.02.1 | B17: ЛСР №01-01, п.1-6 | C17: Демонтаж существующего деревянного причала (правый берег) с погрузкой и транспортировкой на расстояние до 9 км | D17: комплекс | E17: 1
A18: 01.02.2 | B18: ЛСР №01-01, п.7-12 | C18: Демонтаж существующего пирса (правый берег) с погрузкой и транспортировкой на расстояние до 9 км | D18: комплекс | E18: 1
A19: Раздел 1.3. Демонтаж конструкций причала левого берега.
A20: Раздел 1.3.1 Временный пирс (судно-лихтер)
A21: 01.03.1 | B21: ЛСР №01-02 п.1 | C21: Срезка надстроек, возвышающихся над уровнем воды | D21: м | E21: 750
A22: 01.03.2 | B22: ЛСР №01-02 п.2 | C22: Откачка воды из корпуса судна-лихтера передвижным насосом | D22: м3 | E22: 100
A23: 01.03.3 | B23: ЛСР №01-02 п.3 | C23: Очистка трюма судна-лихтера от грунта | D23: м3 | E23: 100
A24: 01.03.4 | B24: ЛСР №01-02 п.4 | C24: Выравнивание берега до пляжного откоса | D24: м3 | E24: 200
A25: 01.03.5 | B25: ЛСР №01-02 п.5, п.6 | C25: Забивка свай фундамента анкерной опоры | D25: т | E25: 6.57
A26: 01.03.6 | B26: ЛСР №01-02 п.7-9 | C26: Монтаж анкерной опоры в виде ростверка | D26: м3 | E26: 12
A27: 01.03.7 | B27: ЛСР №01-02 п.10 | C27: Откачка воды из трюма лихтера | D27: м3 | E27: 200
A28: 01.03.8 | B28: ЛСР №01-02 п.11-12 | C28: Вытаскивание корпуса судна-лихтера на берег | D28: т | E28: 100
A29: 01.03.10 | B29: ЛСР №01-02 п.13 | C29: Демонтаж анкерных опор в виде ростверка | D29: м3 | E29: 12
A30: 01.03.11 | B30: ЛСР №01-02 п.14 | C30: Демонтаж свай | D30: т | E30: 6.57
A31: 01.03.12 | B31: ЛСР №01-02 п.15 | C31: Перевозка автосамосвалами металлолома на расстояние до 10 км | D31: т | E31: 150
A32: Раздел 1.3.2 Временный причал (плашкоут)
A33: 14 | B33: ЛСР №01-02 п.16 | C33: Очистка корпуса плашкоута от грунта экскаватором | D33: м3 | E33: 200
A34: 01.03.13 | B34: ЛСР №01-02 п.17 | C34: Откачка воды из корпуса плашкоута насосами | D34: т | E34: 100
A35: 01.03.14 | B35: ЛСР №01-02 п.18-19 | C35: Вытаскивание корпуса плашкоута на берег | D35: т | E35: 50
A36: 01.03.15 | B36: ЛСР №01-02 п.20 | C36: Перевозка автосамосвалами металлолома на расстояние до 10 км | D36: т | E36: 87
A37: Раздел 1.4. Демонтаж существущего обустройства
A38: 01.04.1 | B38: ЛСР №01-03, п.1-2 | C38: Демонтаж дорожных знаков на металлических стойках с транспортировкой на полигон ТБО на расстояние до 9 км | D38: шт | E38: 4
A39: Глава 2. Причальное сооружение (правый берег)
A40: Раздел 2.1. Конструктивные элементы (правый берег)
C41: Причал
A42: 02.01.1 | B42: ЛСР №02-01-01, п. 1 | C42: Погружение вертикальных свай С-1 | D42: тн | E42: 23.81
A43: 02.01.2 | B43: ЛСР №02-01-01, п. 1 | C43: Погружение вертикальных свай С-2 | D43: тн | E43: 76.73
A44: 02.01.3 | B44: ЛСР №02-01-01, п. 2 | C44: Погружение наклонных свай С-3 | D44: тн | E44: 76.73
A45: 02.01.4 | B45: ЛСР №02-01-01, п. 3, ЛСР 09-02-01 п. 1 | C45: Сваи из стальных труб d=630 мм, толщина стенки 12 мм | D45: тн | E45: 179
A46: 02.01.5 | B46: ЛСР №02-01-01, п. 6 | C46: Установка арматурного каркаса | D46: шт | E46: 67
A47: 02.01.6 | B47: ЛСР №02-01-01, п. 7, ЛСР 09-02-01 п. 1 | C47: Арматурные каркасы | D47: тн | E47: 19.27
A48: 02.01.7 | B48: ЛСР №02-01-01, п. 8-10, ЛСР 09-02-01 п. 1 | C48: Заполнение свай бетоном | D48: м3 | E48: 155.44
A49: 02.01.8 | B49: ЛСР №02-01-01, п. 4-5, ЛСР 09-02-01 п. 1 | C49: Погружение шпунтов | D49: тн | E49: 59.7
A50: 02.01.9 | B50: ЛСР №02-01-01, п. 43-46 | C50: Нанесение вручную праймера на стальную надвобную поверхность сваи (шпунта) | D50: м2 | E50: =201+165 -> 366
A51: 02.01.11 | B51: ЛСР №02-01-01, п. 47-48 | C51: Нанесение обматыванием по спирали ленты на надводную поверхность стальной сваи | D51: м2 | E51: =126+113 -> 239
A52: 02.01.13 | B52: ЛСР №02-01-01, п. 49-50 | C52: Монтаж кожуха на надводную поверхность стальной сваи | D52: м2 | E52: =126+113 -> 239
A53: 02.01.15 | B53: ЛСР №02-01-01, п. 51 | C53: Нанесение мастики на подготовленную стальную поверхность над водой | D53: м2 | E53: 108.2
A54: 02.01.17 | B54: ЛСР №02-01-01, п. 11, ЛСР 09-02-01 п. 1 | C54: Устройство наголовника свай НС-1, НС-2, НС-3 | D54: тн | E54: =1.67+0.9+0.24 -> 2.81
A55: 02.01.18 | B55: ЛСР №02-01-01, п. 12-13, ЛСР 09-02-01 п. 1 | C55: Устройство связи СВ-1, СВ-2, СВ-3 на причале (стальная конструкция) | D55: тн | E55: 4.6328
C56: Возведение верхнего строения пирса
A57: 02.01.19 | B57: ЛСР №02-01-01, п. 52-53, ЛСР 09-02-01 п. 1 | C57: Устройство связи СВ-1, СВ-4, СВ-5 на пирсе (стальная конструкция) | D57: тн | E57: 6.0149
A58: 02.01.20 | B58: ЛСР №02-01-01, п. 61-63, ЛСР 09-02-01 п. 1 | C58: Омоноличивание оголовока пирса | D58: м3 | E58: 16
A59: 02.01.21 | B59: ЛСР №02-01-01, п. 72 | C59: Устройство антисейсмических швов | D59: м | E59: 5.2
A60: 02.01.22 | B60: ЛСР №02-01-01, п. 64, ЛСР 09-02-01 п. 1 | C60: Армирование оголовка пирса | D60: т | E60: =2.5+1.4+0.14 -> 4.04
A61: 02.01.23 | B61: ЛСР №02-01-01, п. 56, | C61: Монтаж каркаса поддерживающего КП-1 из арматуры | D61: т | E61: 0,46
A62: 02.01.24 | B62: ЛСР №02-01-01, п. 54, 55, 57,58, 59, 60, ЛСР 09-02-01 п. 1 | C62: Омоноличивание верхнего строения пирса | D62: м3 | E62: 90
A63: 02.01.25 | B63: ЛСР №02-01-01, п. 65-68 | C63: Устройство колесоотбойников пирса | D63: м3 | E63: 8,1
C64: Возведение верхнего строения причала
A65: 02.01.26 | B65: ЛСР №02-01-01, п. 14, 15 17-18, ЛСР 09-02-01 п. 1 | C65: Омоноличивание верхнего строения причала | D65: м3 | E65: 237
A66: 02.01.27 | B66: ЛСР №02-01-01, п. 40 | C66: Устройство антисейсмических швов | D66: м | E66: 29.2
A67: 02.01.28 | B67: ЛСР №02-01-01, п. 19-22, ЛСР 09-02-01 п. 1 | C67: Устройство колесоотбойников | D67: м3 | E67: 4,2
C68: Поддерживающий каркас
A69: 02.01.29 | B69: ЛСР №02-01-01, п. 16, ЛСР 09-02-01 п. 1 | C69: Монтаж каркаса поддерживающего КП-1 из арматуры | D69: т | E69: 0,46
A70: 02.01.30 | B70: ЛСР №02-01-01, п. 34-37, ЛСР 09-02-01 п. 1 | C70: Устройство монолитного железобетонного массива | D70: м3 | E70: 55
A71: 02.01.31 | B71: ЛСР №02-01-01, п. 32-33 | C71: Устройство бетонной подготовки | D71: м3 | E71: 11
A72: 02.01.32 | B72: ЛСР №02-01-01, п. 37-39 | C72: Укрепление подпричального откоса камнем | D72: м3 | E72: =352+470 -> 822
A73: 02.01.33 | B73: ЛСР №02-01-01, п. 73-74 | C73: Обваловка свай пирса камнем | D73: м3 | E73: 328
C74: Элементы обустройства
A75: 02.01.34 | B75: ЛСР №02-01-01, п. 41-42 | C75: Монтаж шлагбаума | D75: шт | E75: 6
A76: 02.01.35 | B76: ЛСР №02-01-01, п. 27, 23-24, ЛСР 09-02-01 п. 1 | C76: Установка стального перильного ограждения | D76: м | E76: 75.6
A77: 02.01.36 | B77: ЛСР №02-01-01, п. 25, ЛСР 09-02-01 п. 1 | C77: Навеска отбойных устройств | D77: тн | E77: 4.6
A78: 02.01.37 | B78: ЛСР №02-01-01, п. 26 | C78: Монтаж стальных скоб-трапов | D78: тн | E78: 0.072
A79: 02.01.38 | B79: ЛСР №02-01-01, п. 28-30, 69, 70 | C79: Установка швартовых тумб | D79: шт | E79: 4
A80: 02.01.39 | B80: ЛСР №02-01-01, п. 75-76 | C80: Установка светодиодных сигнальных огоней для причалов | D80: шт. | E80: 5
A81: Раздел 2.2. Дноуглубительные работы
A82: 02.02.1 | B82: ЛСР №02-01-02, п. 1 | C82: Дноуглубительные работы | D82: м3 | E82: 1249
A83: Раздел 2.3. Перенос автобусного павильона для пассажиров. Правый берег
A84: 02.03.1 | B84: ЛСР №02-01-03, п. 1-6 | C84: Демонтаж существующего автопавильона с погрузкой и транспортировкой на временную площадку складирования | D84: шт | E84: 1
A85: 02.03.2 | B85: ЛСР №02-01-03, п. 7-8 | C85: Погрузка и доставка элементов существующего автопавильона от временной площадки складирования до места работ | D85: шт | E85: 1
A86: 02.03.3 | B86: ЛСР №02-01-03, п. 9-29, ЛСР 09-02-01 п. 1 | C86: Монтаж железобетонного автобусного павильона с установкой скамьи, урны | D86: шт | E86: 1
A87: Раздел 2.4. Подъездная дорога. Правый берег
A88: Раздел 2.4.1 Восстановление покрытия
C89: Замена пучинистого основания
A90: 02.04.1 | B90: ЛСР №02-01-04, п. 1 | C90: Фрезеровка существующего асфальтобетона с погрузкой в автосамосвалы и транспортировкой до 9 км | D90: м2 | E90: 130
A91: 02.04.2 | B91: ЛСР №02-01-04, п. 2, 4 | C91: Разработка грунта 1 группы, y=1,70 т/м3, экскаватором с емкостью ковша 1,0 м3 с последующей погрузкой в автосамосвалы и транспортировкой до 9 км | D91: м3 | E91: 505
A92: 02.04.3 | B92: ЛСР №02-01-04, п. 3 | C92: Разработка крупнообломочного грунта 4 группы y=2,26 т/м3 экскаватором емкостью ковша 1,0 м3 с погрузкой и транспортировкой на расстояние до 43 км в основание дорожной одежды из карьера (км 381 а/д Мильково-Ключи-Усть-Камчатск) | D92: м3 | E92: 505
A93: 02.04.4 | B93: ЛСР №02-01-04, п. 5-6 | C93: Уплотнение грунта | D93: м3 | E93: 505
C94: Устройство новой дорожной на сопряжении с причальным сооружением
A95: 02.04.5 | B95: ЛСР №02-01-04, п. 11-17, ЛСР 09-02-01 п. 1 | C95: Устройство покрытия цементобетонного толщиной 10 см | D95: м2 | E95: 191
A96: 02.04.6 | B96: ЛСР №02-01-04, п. 9-10, ЛСР 09-02-01 п. 1 | C96: Устройство верхнего слоя основания из фракционированного щебня, уложенного по способу заклинки, толщиной 20 см | D96: м2 | E96: 191
A97: 02.04.7 | B97: ЛСР №02-01-04, п. 7-8 | C97: Устройство нижнего слоя основания из щебеночно-песчаной смеси С5, толщиной 29 см | D97: м3 | E97: 71.9
C98: Устройство новой дорожной одежды на остановочной площадке автобусной остановки
A99: 02.04.8 | B99: ЛСР №02-01-04, п. 22-24, ЛСР 09-02-01 п. 1 | C99: Устройство покрытия цементобетонного толщиной 10 см | D99: м2 | E99: 46
A100: 02.04.9 | B100: ЛСР №02-01-04, п. 20-21, ЛСР 09-02-01 п. 1 | C100: Устройство верхнего слоя основания из фракционированного щебня, уложенного по способу заклинки, толщиной 20 см, в т.ч.: | D100: м2 | E100: 46
A101: 02.04.10 | B101: ЛСР №02-01-04, п. 18-19 | C101: Устройство нижнего слоя основания из щебеночно-песчаной смеси С5, толщиной 29 см | D101: м3 | E101: 16.27
C102: Устройство тротуара
...

Sheet НМЦК СК
O1: УТВЕРЖДАЮ
O2: Начальник КГКУ "Камчатуправтодор"
O3: ______________О.В. Булах
O4: «____»______________2022 г.
A6: Расчет начальной (максимальной) цены контракта
A7: на оказание услуг по осуществлению строительного контроля за объектом: "Строитсльство причальных сооружений через протоку Озерная в Усть-Камчатском районе Камчатского края"
A8: Основания для расчета:
A9: ='НМЦК подряд'!A10:F10 -> 1. Приказ КГКУ "Камчатуправтодор" от 29.07.2022г. №402 Об утверждении проектной документации "Строительство причальных сооружений через протоку Озерная в Усть-Камчатском районе Камчатского края"
A10: ='НМЦК подряд'!A11:F11 -> 2. Положительное заключение государственной экспертизы проектной документации и результатов инженерных изысканий №41-1-1-2-049246-2022 от 22.07.2022г.
A11: 3. Утвержденный сводный сметный расчет
Q12: руб.
A13: Наименование работ и затрат | B13: Стоимость работ в ценах на дату утверждения сметной документации / 1 квартал 2022 года | C13: Индекс фактической инфляции | D13: Стоимость работ в ценах на дату формирования начальной (максимальной) цены контракта | F13: Индекс прогнозной инфляции на период выполнения работ | H13: Начальная (максимальная) цена контракта с учетом индекса прогнозной инфляции на период выполнения работ | L13: Распределение по годам (в ценах 1 квартала 2022 года) | O13: Распределение по годам (с учетом индексов фактической и прогнозной инфляции)
L14: 2025 | M14: 2026 | N14: 2027 | O14: 2025 | P14: 2026 | Q14: 2027
A15: 1 | B15: 2 | C15: 3 | D15: 4 | F15: 5 | H15: 6 | L15: 7 | M15: 8 | N15: 9 | O15: 10 | P15: 11 | Q15: 12
A16: Затраты на осуществление строительного контроля предусмотренные проектно-сметной документацией (2,14%) | B16: =Затраты!I16*1000/1.2 -> 4228440 | C16: =C34 -> 1.3062 | D16: =B16*C16 -> 5523188 | F16: =H61 -> 0 | H16: =D16*F16 -> 0 | L16: =B16*D49 -> 0 | M16: =B16*D50 -> 2306403 | N16: =B16*D51 -> 1922037 | O16: =H16*D49 -> 0 | P16: =H16*D50 -> 0 | Q16: =H16*D51 -> 0
A17: НДС (20%) | B17: =B16*20% -> 845688 | D17: =D16*20% -> 1104638 | H17: =H16*20% -> 0 | L17: =L16*20% -> 0 | M17: =M16*20% -> 461281 | N17: =N16*20% -> 384407 | O17: =O16*20% -> 0 | P17: =P16*20% -> 0 | Q17: =Q16*20% -> 0
A18: Стоимость с учетом НДС | B18: =B16+B17 -> 5074128 | D18: =SUM(D16:E17) -> 6627826 | H18: =SUM(H16:K17) -> 0 | L18: =L16+L17 -> 0 | M18: =M16+M17 -> 2767684 | N18: =N16+N17 -> 2306444 | O18: =O16+O17 -> 0 | P18: =P16+P17 -> 0 | Q18: =Q16+Q17 -> 0
A19: *В зависимости от года утверждения ПСД и планируемого выполнения работ по годам исполнения государственного контракта таблица может быть откорректирована.
A21: Дата формирования НМЦК - | B21: ноябрь 2022 года
A22: Начало оказания услуг - апрель 2023 года
A23: Окончание оказания услуг - ноябрь 2024 года
A25: 1. Расчет индекса фактической инфляции с использованием ИПЦ Росстата (Камчатский край):
A27: =Справка!A24 -> март 2023 / март 2022 | B27: =Справка!B24 -> 108.6 | C27: =B27/100 -> 1.086
A28: =Справка!A25 -> март 2024 / март 2023 | B28: =Справка!B25 -> 109.53 | C28: =B28/100 -> 1.0953
A29: =Справка!A26 -> март 2025 / март 2024 | B29: =Справка!B26 -> 106.56 | C29: =B29/100 -> 1.0656
A30: =Справка!A27 -> 45748 | B30: =Справка!B27 -> 98.08 | C30: =B30/100 -> 0.9808
A31: =Справка!A28 -> 45778 | B31: =Справка!B28 -> 101.17 | C31: =B31/100 -> 1.0117
A32: =Справка!A29 -> 45809 | B32: =Справка!B29 -> 103.19 | C32: =B32/100 -> 1.0319
A33: =Справка!A30 -> 45839 | B33: =Справка!B30 -> 100.64 | C33: =B33/100 -> 1.0064
B34: Индекс фактической инфляции | C34: =C27*C28*C29*C30*C31*C32*C33 -> 1.3062
A36: 2. Расчет индекса прогнозной инфляции (Прогноз социально-экономического развития Камчатского края на 2023-2025 гг. от 06.07.2022г., отрасль "Инвестиции в основной капитал"):
A39: 2025 = | G39: 12 | H39: √ | I39: =B40 -> 0 | J39: = | K39: =I39^(1/G39) -> 0
B40: =Справка!F26 -> 0 | C40: Ежемесячный индекс прогноз на 2025 =
A42: 2026 = | G42: 12 | H42: √ | I42: =B43 -> 1.078 | J42: = | K42: =I42^(1/G42) -> 1.0063
B43: =Справка!F41 -> 1.078 | C43: Ежемесячный индекс прогноз на 2026 =
A45: 2027 = | G45: 12 | H45: √ | I45: =B46 -> 1.077 | J45: = | K45: =I45^(1/G45) -> 1.0062
B46: =Справка!F44 -> 1.077 | C46: Ежемесячный индекс прогноз на 2027 =
A49: Доля сметной стоимости подлежащая выполнению в 2025 году - | D49: =ROUND(F49/(F49+F50+F51),5) -> 0 | F49: 0 | G49: мес.
A50: Доля сметной стоимости подлежащая выполнению в 2026 году - | D50: =ROUND(F50/(F50+F51+F49),5) -> 0.54545 | F50: 12 | G50: мес.
A51: Доля сметной стоимости подлежащая выполнению в 2027 году - | D51: =ROUND(F51/(F51+F50+F49),5) -> 0.45455 | F51: 10 | G51: мес.
A53: С учетом полученных данных вычисляются прогнозные индексы для каждого периода исполнения контракта:
A55: К на 2025 год = | B55: (1,01402-1) / 2 + 1 = ( | C55: =D64 -> 0 | D55: - 1) / 2 +1 = | E55: =(C55-1)/2+1 -> 0.5
A57: К на 2026 год = | B57: 1,014012-10*(1,00494+1,004912) / 2 = | D57: =D65 -> 0 | E57: * ( | F57: =D67 -> 1.0063 | G57: + | H57: =D68 -> 1.0783 | J57: ) / 2 = | L57: =ROUND(D57*(F57+H57)/2,4) -> 0
A59: К на 2027 год = | B59: 1,014012-10*1,004912 * ((1,0045+1,004511) / 2) = | E59: =D65 -> 0 | F59: * | G59: =D68 -> 1.0783 | H59: * ( | I59: =D70 -> 1.0062 | K59: + | L59: =D71 -> 1.0638 | M59: ) / 2 = | N59: =ROUND(E59*G59*(I59+L59)/2,4) -> 0
A61: Индекс прогнозной инфляции на период выполнения работ = | D61: =CONCATENATE(D49,"*",E55,"+",D50,"*",L57,"+",D51,"*",N59," =",) -> 0*0,5+0,54545*0+0,45455*0 = | H61: =D49*E55+D50*L57+D51*N59 -> 0
A63: Ежемесячный прогнозный индекс | E63: ст-нь | G63: период
B64: 2025 | C64: =K39 -> 0 | D64: =POWER(C64,E64) -> 0 | E64: 5 | F64: август-декабрь 2025
C65: =C64 -> 0 | D65: =POWER(C65,E65) -> 0 | E65: 5 | F65: август -декабрь 2025
B67: 2026 | C67: =K42 -> 1.0063 | D67: =POWER(C67,E67) -> 1.0063 | E67: 1 | F67: январь 2026
C68: =C67 -> 1.0063 | D68: =POWER(C68,E68) -> 1.0783 | E68: 12 | F68: январь-декабрь 2026
B70: 2027 | C70: =K45 -> 1.0062 | D70: =POWER(C70,E70) -> 1.0062 | E70: 1 | F70: январь 2027
C71: =C70 -> 1.0062 | D71: =POWER(C71,E71) -> 1.0638 | E71: 10 | F71: январь-октябрь 2027
B72: Составил | C72: Главный эксперт дорожного хозяйства отдела строительства, реконструкции, капитального ремонта автомобильных дорог и сооружений на них | N72: А.А. Терновая
B73: Проверил | C73: Начальник отдела строительства, реконструкции, капитального ремонта автомобильных дорог и сооружений на них | N73: О.А. Мельник
B74: Согласовал | C74: Заместитель начальника КГКУ "Камчатуправтодор" | N74: А.Л. Нейштадт

Sheet НМЦК АН
O1: УТВЕРЖДАЮ
O2: И.о. начальника КГКУ "Камчатуправтодор"
O3: ______________А.Л. Нейштадт
O4: «____»______________2022 г.
A6: Расчет начальной (максимальной) цены контракта
A7: на оказание услуг по осуществлению авторского надзора за объектом: "Строитсльство причальных сооружений через протоку Озерная в Усть-Камчатском районе Камчатского края"
A8: Основания для расчета:
A9: ='НМЦК подряд'!A10:F10 -> 1. Приказ КГКУ "Камчатуправтодор" от 29.07.2022г. №402 Об утверждении проектной документации "Строительство причальных сооружений через протоку Озерная в Усть-Камчатском районе Камчатского края"
A10: ='НМЦК подряд'!A11:F11 -> 2. Положительное заключение государственной экспертизы проектной документации и результатов инженерных изысканий №41-1-1-2-049246-2022 от 22.07.2022г.
A11: 3. Утвержденный сводный сметный расчет
Q12: руб.
A13: Наименование работ и затрат | B13: Стоимость работ в ценах на дату утверждения сметной документации / 1 квартал 2022 года | C13: Индекс фактической инфляции | D13: Стоимость работ в ценах на дату формирования начальной (максимальной) цены контракта | F13: Индекс прогнозной инфляции на период выполнения работ | H13: Начальная (максимальная) цена контракта с учетом индекса прогнозной инфляции на период выполнения работ | L13: Распределение по годам (в ценах 1 квартала 2022 года) | O13: Распределение по годам (с учетом индексов фактической и прогнозной инфляции)
L14: 2022 | M14: 2023 | N14: 2024 | O14: 2022 | P14: 2023 | Q14: 2024
A15: 1 | B15: 2 | C15: 3 | D15: 4 | F15: 5 | H15: 6 | L15: 7 | M15: 8 | N15: 9 | O15: 10 | P15: 11 | Q15: 12
A16: Затраты на осуществление авторского надзора предусмотренные проектно-сметной документацией (0,2%) | B16: 408681 | C16: =C35 -> 1.3062 | D16: =B16*C16 -> 533819 | F16: =H62 -> 0 | H16: =D16*F16 -> 0 | L16: 0 | M16: =B16*D51 -> 0 | N16: =B16*D52+1 -> 408682 | O16: =H16*D50 -> 0 | P16: =H16*D51 -> 0 | Q16: =H16*D52 -> 0
A17: НДС (20%) | B17: =B16*0.22 -> 89910 | D17: =D16*0.22 -> 117440 | M17: =M16*0.22 -> 0 | N17: =N16*0.22 -> 89910
A18: Стоимость с учетом НДС | B18: =B16*1.22 -> 498591 | D18: =D16+D17 -> 651259 | H18: =SUM(H16:K17) -> 0 | L18: =L16+L17 -> 0 | M18: =M16+M17 -> 0 | N18: =N16+N17 -> 498592 | O18: =O16+O17 -> 0 | P18: =P16+P17 -> 0 | Q18: =Q16+Q17 -> 0
A19: *В зависимости от года утверждения ПСД и планируемого выполнения работ по годам исполнения государственного контракта таблица может быть откорректирована.
A21: Дата формирования НМЦК - | B21: октябрь 2022 года
A22: Начало оказания услуг - ноябрь 2022 года
A23: Окончание оказания услуг - ноябрь 2024 года
A25: 1. Расчет индекса фактической инфляции с использованием ИПЦ Росстата (Камчатский край):
A27: ='НМЦК СК'!A27 -> март 2023 / март 2022 | B27: ='НМЦК СК'!B27 -> 108.6 | C27: =B27/100 -> 1.086
A28: ='НМЦК СК'!A28 -> март 2024 / март 2023 | B28: ='НМЦК СК'!B28 -> 109.53 | C28: =B28/100 -> 1.0953
A29: ='НМЦК СК'!A29 -> март 2025 / март 2024 | B29: ='НМЦК СК'!B29 -> 106.56 | C29: =B29/100 -> 1.0656
A30: ='НМЦК СК'!A30 -> 45748 | B30: ='НМЦК СК'!B30 -> 98.08 | C30: =B30/100 -> 0.9808
A31: ='НМЦК СК'!A31 -> 45778 | B31: ='НМЦК СК'!B31 -> 101.17 | C31: =B31/100 -> 1.0117
A32: ='НМЦК СК'!A32 -> 45809 | B32: ='НМЦК СК'!B32 -> 103.19 | C32: =B32/100 -> 1.0319
A33: ='НМЦК СК'!A33 -> 45839 | B33: ='НМЦК СК'!B33 -> 100.64 | C33: =B33/100 -> 1.0064
B35: Индекс фактической инфляции | C35: =C27*C28*C29*C30*C31*C32*C33 -> 1.3062
A37: 2. Расчет индекса прогнозной инфляции (Прогноз социально-экономического развития Камчатского края на 2023-2025 гг. от 06.07.2022г., отрасль "Инвестиции в основной капитал"):
A40: 2022 = | G40: 12 | H40: √ | I40: =B41 -> 0 | J40: = | K40: =I40^(1/G40) -> 0
B41: =Справка!F26 -> 0 | C41: Ежемесячный индекс прогноз на 2022 =
A43: 2023 = | G43: 12 | H43: √ | I43: =B44 -> 1.078 | J43: = | K43: =I43^(1/G43) -> 1.0063
B44: =Справка!F41 -> 1.078 | C44: Ежемесячный индекс прогноз на 2023 =
A46: 2024 = | G46: 12 | H46: √ | I46: =B47 -> 1.077 | J46: = | K46: =I46^(1/G46) -> 1.0062
B47: =Справка!F44 -> 1.077 | C47: Ежемесячный индекс прогноз на 2024 =
A50: Доля сметной стоимости подлежащая выполнению в 2022 году - | D50: =ROUND(F50/(F50+F51+F52),5) -> 0 | F50: 0 | G50: мес.
A51: Доля сметной стоимости подлежащая выполнению в 2023 году - | D51: 0 | F51: 2 | G51: мес.
A52: Доля сметной стоимости подлежащая выполнению в 2024 году - | D52: 1 | F52: 2 | G52: мес.
A54: С учетом полученных данных вычисляются прогнозные индексы для каждого периода исполнения контракта:
A56: К на 2022 год = | B56: (1,01402-1) / 2 + 1 = ( | C56: =D65 -> 0 | D56: - 1) / 2 +1 = | E56: =(C56-1)/2+1 -> 0.5
A58: К на 2023 год = | B58: 1,014012-10*(1,0049+1,004912) / 2 = | D58: =D65 -> 0 | E58: * ( | F58: =D68 -> 1.0063 | G58: + | H58: =D69 -> 1.0783 | J58: ) / 2 = | L58: =ROUND(D58*(F58+H58)/2,4) -> 0
A60: К на 2024 год = | B60: 1,014012-10*1,004912 * ((1,0045+1,004511) / 2) = | E60: =D65 -> 0 | F60: * | G60: =D69 -> 1.0783 | H60: * ( | I60: =D71 -> 1.0062 | K60: + | L60: =D72 -> 1.0638 | M60: ) / 2 = | N60: =ROUND(E60*G60*(I60+L60)/2,4) -> 0
A62: Индекс прогнозной инфляции на период выполнения работ = | D62: =CONCATENATE(D50,"*",E56,"+",D51,"*",L58,"+",D52,"*",N60," =",) -> 0*0,5+0*0+1*0 = | H62: =D50*E56+D51*L58+D52*N60 -> 0
A64: Ежемесячный прогнозный индекс | E64: ст-нь | G64: период
A65: 2022 | C65: ='НМЦК СК'!C64 -> 0 | D65: ='НМЦК СК'!D64 -> 0 | E65: 5 | G65: ноябрь-декабрь 2022
C66: ='НМЦК СК'!C65 -> 0 | D66: ='НМЦК СК'!D65 -> 0
A67: 2023 | E67: 12 | G67: январь-декабрь 2023
A68: 2024 | C68: ='НМЦК СК'!C67 -> 1.0063 | D68: ='НМЦК СК'!D67 -> 1.0063 | E68: 11 | G68: январь-ноябрь 2024
C69: ='НМЦК СК'!C68 -> 1.0063 | D69: ='НМЦК СК'!D68 -> 1.0783
C71: ='НМЦК СК'!C70 -> 1.0062 | D71: ='НМЦК СК'!D70 -> 1.0062
C72: ='НМЦК СК'!C71 -> 1.0062 | D72: ='НМЦК СК'!D71 -> 1.0638
B86: Составил | C86: Главный эксперт дорожного хозяйства отдела строительства, реконструкции, капитального ремонта автомобильных дорог и сооружений на них | N86: А.А. Терновая
B87: Проверил | C87: Начальник отдела строительства, реконструкции, капитального ремонта автомобильных дорог и сооружений на них | N87: О.А. Мельник
B88: Согласовал | C88: Заместитель начальника КГКУ "Камчатуправтодор" | N88: А.Л. Нейштадт
